[
  {
    "album": {
      "artists": [
        {
          "external_urls": {
            "spotify": "https://open.spotify.com/artist/3TVXtAsR1Inumwj472S9r4"
          },
          "href": "https://api.spotify.com/v1/artists/3TVXtAsR1Inumwj472S9r4",
          "id": "3TVXtAsR1Inumwj472S9r4",
          "name": "Drake",
          "type": "artist",
          "uri": "spotify:artist:3TVXtAsR1Inumwj472S9r4"
        },
        {
          "external_urls": {
            "spotify": "https://open.spotify.com/artist/1URnnhqYAYcrqrcwql10ft"
          },
          "href": "https://api.spotify.com/v1/artists/1URnnhqYAYcrqrcwql10ft",
          "id": "1URnnhqYAYcrqrcwql10ft",
          "name": "21 Savage",
          "type": "artist",
          "uri": "spotify:artist:1URnnhqYAYcrqrcwql10ft"
        }
      ],
      "href": "https://api.spotify.com/v1/albums/5MS3MvWHJ3lOZPLiMxzOU6",
      "images": [
        {
          "height": 640,
          "url": "https://i.scdn.co/image/ab67616d0000b27302854a7060fccc1a66a4b5ad",
          "width": 640
        },
        {
          "height": 300,
          "url": "https://i.scdn.co/image/ab67616d00001e0202854a7060fccc1a66a4b5ad",
          "width": 300
        },
        {
          "height": 64,
          "url": "https://i.scdn.co/image/ab67616d0000485102854a7060fccc1a66a4b5ad",
          "width": 64
        }
      ],
      "name": "Her Loss",
      "release_date": "2022-11-04",
      "release_date_precision": "day",
      "total_tracks": 16,
      "type": "album",
      "uri": "spotify:album:5MS3MvWHJ3lOZPLiMxzOU6"
    },
    "artists": [
      {
        "external_urls": {
          "spotify": "https://open.spotify.com/artist/3TVXtAsR1Inumwj472S9r4"
        },
        "href": "https://api.spotify.com/v1/artists/3TVXtAsR1Inumwj472S9r4",
        "id": "3TVXtAsR1Inumwj472S9r4",
        "name": "Drake",
        "type": "artist",
        "uri": "spotify:artist:3TVXtAsR1Inumwj472S9r4"
      },
      {
        "external_urls": {
          "spotify": "https://open.spotify.com/artist/1URnnhqYAYcrqrcwql10ft"
        },
        "href": "https://api.spotify.com/v1/artists/1URnnhqYAYcrqrcwql10ft",
        "id": "1URnnhqYAYcrqrcwql10ft",
        "name": "21 Savage",
        "type": "artist",
        "uri": "spotify:artist:1URnnhqYAYcrqrcwql10ft"
      }
    ],
    "explicit": true,
    "href": "https://api.spotify.com/v1/tracks/7GeTsDIc5ykNB6lORO6Cee",
    "is_local": false,
    "name": "Circo Loco",
    "preview_url": null
  }
]