[
  {
    "genres": [
      "rap"
    ],
    "href": "https://api.spotify.com/v1/artists/3TVXtAsR1Inumwj472S9r4",
    "id": "3TVXtAsR1Inumwj472S9r4",
    "images": [
      {
        "height": 640,
        "url": "https://i.scdn.co/image/ab6761610000e5eb4293385d324db8558179afd9",
        "width": 640
      },
      {
        "height": 320,
        "url": "https://i.scdn.co/image/ab676161000051744293385d324db8558179afd9",
        "width": 320
      },
      {
        "height": 160,
        "url": "https://i.scdn.co/image/ab6761610000f1784293385d324db8558179afd9",
        "width": 160
      }
    ],
    "name": "Drake",
    "type": "artist",
    "uri": "spotify:artist:3TVXtAsR1Inumwj472S9r4"
  },
  {
    "genres": [
      "reggaeton",
      "trap latino",
      "urbano latino",
      "latin"
    ],
    "href": "https://api.spotify.com/v1/artists/4q3ewBCX7sLwd24euuV69X",
    "id": "4q3ewBCX7sLwd24euuV69X",
    "images": [
      {
        "height": 640,
        "url": "https://i.scdn.co/image/ab6761610000e5eb81f47f44084e0a09b5f0fa13",
        "width": 640
      },
      {
        "height": 320,
        "url": "https://i.scdn.co/image/ab6761610000517481f47f44084e0a09b5f0fa13",
        "width": 320
      },
      {
        "height": 160,
        "url": "https://i.scdn.co/image/ab6761610000f17881f47f44084e0a09b5f0fa13",
        "width": 160
      }
    ],
    "name": "Bad Bunny",
    "type": "artist",
    "uri": "spotify:artist:4q3ewBCX7sLwd24euuV69X"
  },
  {
    "genres": [
      "indie rock"
    ],
    "href": "https://api.spotify.com/v1/artists/0XNa1vTidXlvJ2gHSsRi4A",
    "id": "0XNa1vTidXlvJ2gHSsRi4A",
    "images": [
      {
        "height": 640,
        "url": "https://i.scdn.co/image/ab6761610000e5eb69ecfa7557856564c968640d",
        "width": 640
      },
      {
        "height": 320,
        "url": "https://i.scdn.co/image/ab6761610000517469ecfa7557856564c968640d",
        "width": 320
      },
      {
        "height": 160,
        "url": "https://i.scdn.co/image/ab6761610000f17869ecfa7557856564c968640d",
        "width": 160
      }
    ],
    "name": "Franz Ferdinand",
    "type": "artist",
    "uri": "spotify:artist:0XNa1vTidXlvJ2gHSsRi4A"
  },
  {
    "genres": [
      "funk rock",
      "alternative rock",
      "rock"
    ],
    "href": "https://api.spotify.com/v1/artists/0L8ExT028jH3ddEcZwqJJ5",
    "id": "0L8ExT028jH3ddEcZwqJJ5",
    "images": [
      {
        "height": 640,
        "url": "https://i.scdn.co/image/ab6761610000e5ebc33cc15260b767ddec982ce8",
        "width": 640
      },
      {
        "height": 320,
        "url": "https://i.scdn.co/image/ab67616100005174c33cc15260b767ddec982ce8",
        "width": 320
      },
      {
        "height": 160,
        "url": "https://i.scdn.co/image/ab6761610000f178c33cc15260b767ddec982ce8",
        "width": 160
      }
    ],
    "name": "Red Hot Chili Peppers",
    "type": "artist",
    "uri": "spotify:artist:0L8ExT028jH3ddEcZwqJJ5"
  },
  {
    "genres": [
      "garage rock",
      "indie rock",
      "alternative rock"
    ],
    "href": "https://api.spotify.com/v1/artists/0epOFNiUfyON9EYx7Tpr6V",
    "id": "0epOFNiUfyON9EYx7Tpr6V",
    "images": [
      {
        "height": 640,
        "url": "https://i.scdn.co/image/ab6761610000e5ebc3b137793230f4043feb0089",
        "width": 640
      },
      {
        "height": 320,
        "url": "https://i.scdn.co/image/ab67616100005174c3b137793230f4043feb0089",
        "width": 320
      },
      {
        "height": 160,
        "url": "https://i.scdn.co/image/ab6761610000f178c3b137793230f4043feb0089",
        "width": 160
      }
    ],
    "name": "The Strokes",
    "type": "artist",
    "uri": "spotify:artist:0epOFNiUfyON9EYx7Tpr6V"
  },
  {
    "genres": [
      "rock en español",
      "latin rock",
      "mexican rock",
      "latin pop"
    ],
    "href": "https://api.spotify.com/v1/artists/7okwEbXzyT2VffBmyQBWLz",
    "id": "7okwEbXzyT2VffBmyQBWLz",
    "images": [
      {
        "height": 640,
        "url": "https://i.scdn.co/image/ab6761610000e5eb152dcec8175d19fb12eeb8e0",
        "width": 640
      },
      {
        "height": 320,
        "url": "https://i.scdn.co/image/ab67616100005174152dcec8175d19fb12eeb8e0",
        "width": 320
      },
      {
        "height": 160,
        "url": "https://i.scdn.co/image/ab6761610000f178152dcec8175d19fb12eeb8e0",
        "width": 160
      }
    ],
    "name": "Maná",
    "type": "artist",
    "uri": "spotify:artist:7okwEbXzyT2VffBmyQBWLz"
  },
  {
    "genres": [
      "latin pop"
    ],
    "href": "https://api.spotify.com/v1/artists/0EmeFodog0BfCgMzAIvKQp",
    "id": "0EmeFodog0BfCgMzAIvKQp",
    "images": [
      {
        "height": 640,
        "url": "https://i.scdn.co/image/ab6761610000e5eb44b07362e94585ebd7c564c9",
        "width": 640
      },
      {
        "height": 320,
        "url": "https://i.scdn.co/image/ab6761610000517444b07362e94585ebd7c564c9",
        "width": 320
      },
      {
        "height": 160,
        "url": "https://i.scdn.co/image/ab6761610000f17844b07362e94585ebd7c564c9",
        "width": 160
      }
    ],
    "name": "Shakira",
    "type": "artist",
    "uri": "spotify:artist:0EmeFodog0BfCgMzAIvKQp"
  },
  {
    "genres": [
      "rock en español",
      "latin rock",
      "mexican rock"
    ],
    "href": "https://api.spotify.com/v1/artists/60uh2KYYSCqAgJNxcU4DA0",
    "id": "60uh2KYYSCqAgJNxcU4DA0",
    "images": [
      {
        "height": 640,
        "url": "https://i.scdn.co/image/ab6761610000e5ebf00d7551907825539d1dc034",
        "width": 640
      },
      {
        "height": 320,
        "url": "https://i.scdn.co/image/ab67616100005174f00d7551907825539d1dc034",
        "width": 320
      },
      {
        "height": 160,
        "url": "https://i.scdn.co/image/ab6761610000f178f00d7551907825539d1dc034",
        "width": 160
      }
    ],
    "name": "Hombres G",
    "type": "artist",
    "uri": "spotify:artist:60uh2KYYSCqAgJNxcU4DA0"
  },
  {
    "genres": [
      "indie",
      "garage rock"
    ],
    "href": "https://api.spotify.com/v1/artists/7Ln80lUS6He07XvHI8qqHH",
    "id": "7Ln80lUS6He07XvHI8qqHH",
    "images": [
      {
        "height": 640,
        "url": "https://i.scdn.co/image/ab6761610000e5eb7da39dea0a72f581535fb11f",
        "width": 640
      },
      {
        "height": 320,
        "url": "https://i.scdn.co/image/ab676161000051747da39dea0a72f581535fb11f",
        "width": 320
      },
      {
        "height": 160,
        "url": "https://i.scdn.co/image/ab6761610000f1787da39dea0a72f581535fb11f",
        "width": 160
      }
    ],
    "name": "Arctic Monkeys",
    "type": "artist",
    "uri": "spotify:artist:7Ln80lUS6He07XvHI8qqHH"
  },
  {
    "genres": [
      "classic rock",
      "yacht rock",
      "soft rock"
    ],
    "href": "https://api.spotify.com/v1/artists/08GQAI4eElDnROBrJRGE0X",
    "id": "08GQAI4eElDnROBrJRGE0X",
    "images": [
      {
        "height": 640,
        "url": "https://i.scdn.co/image/ab6761610000e5ebc8752dd511cda8c31e9daee8",
        "width": 640
      },
      {
        "height": 320,
        "url": "https://i.scdn.co/image/ab67616100005174c8752dd511cda8c31e9daee8",
        "width": 320
      },
      {
        "height": 160,
        "url": "https://i.scdn.co/image/ab6761610000f178c8752dd511cda8c31e9daee8",
        "width": 160
      }
    ],
    "name": "Fleetwood Mac",
    "type": "artist",
    "uri": "spotify:artist:08GQAI4eElDnROBrJRGE0X"
  },
  {
    "genres": [],
    "href": "https://api.spotify.com/v1/artists/4gzpq5DPGxSnKTe4SA8HAU",
    "id": "4gzpq5DPGxSnKTe4SA8HAU",
    "images": [
      {
        "height": 640,
        "url": "https://i.scdn.co/image/ab6761610000e5eb1ba8fc5f5c73e7e9313cc6eb",
        "width": 640
      },
      {
        "height": 320,
        "url": "https://i.scdn.co/image/ab676161000051741ba8fc5f5c73e7e9313cc6eb",
        "width": 320
      },
      {
        "height": 160,
        "url": "https://i.scdn.co/image/ab6761610000f1781ba8fc5f5c73e7e9313cc6eb",
        "width": 160
      }
    ],
    "name": "Coldplay",
    "type": "artist",
    "uri": "spotify:artist:4gzpq5DPGxSnKTe4SA8HAU"
  },
  {
    "genres": [
      "colombian pop",
      "latin pop"
    ],
    "href": "https://api.spotify.com/v1/artists/1mux8L6xg2Cmrc7k0wQczl",
    "id": "1mux8L6xg2Cmrc7k0wQczl",
    "images": [
      {
        "height": 640,
        "url": "https://i.scdn.co/image/ab6761610000e5eb2ac7dc75e8e0ba7ae2e03158",
        "width": 640
      },
      {
        "height": 320,
        "url": "https://i.scdn.co/image/ab676161000051742ac7dc75e8e0ba7ae2e03158",
        "width": 320
      },
      {
        "height": 160,
        "url": "https://i.scdn.co/image/ab6761610000f1782ac7dc75e8e0ba7ae2e03158",
        "width": 160
      }
    ],
    "name": "Bacilos",
    "type": "artist",
    "uri": "spotify:artist:1mux8L6xg2Cmrc7k0wQczl"
  },
  {
    "genres": [
      "rock en español",
      "latin rock",
      "argentine rock",
      "mexican rock",
      "latin alternative"
    ],
    "href": "https://api.spotify.com/v1/artists/4TK1gDgb7QKoPFlzRrBRgR",
    "id": "4TK1gDgb7QKoPFlzRrBRgR",
    "images": [
      {
        "height": 1000,
        "url": "https://i.scdn.co/image/0a44319db623b112c3fddca7a1ef88b5756265cd",
        "width": 1000
      },
      {
        "height": 640,
        "url": "https://i.scdn.co/image/1c47795e21794ab947aa466283026148163d4bf5",
        "width": 640
      },
      {
        "height": 200,
        "url": "https://i.scdn.co/image/f611096759364ce80a459c8fcc3e47d789ba34a7",
        "width": 200
      },
      {
        "height": 64,
        "url": "https://i.scdn.co/image/4957431c9881f30a238aeb0c2bc76e05e6a46831",
        "width": 64
      }
    ],
    "name": "Los Enanitos Verdes",
    "type": "artist",
    "uri": "spotify:artist:4TK1gDgb7QKoPFlzRrBRgR"
  },
  {
    "genres": [],
    "href": "https://api.spotify.com/v1/artists/5NGO30tJxFlKixkPSgXcFE",
    "id": "5NGO30tJxFlKixkPSgXcFE",
    "images": [
      {
        "height": 641,
        "url": "https://i.scdn.co/image/1f73a61faca2942cd5ea29c2143184db8645f0b3",
        "width": 1000
      },
      {
        "height": 410,
        "url": "https://i.scdn.co/image/72fe2cadb69ab59960ae3dbd29618549e4432699",
        "width": 640
      },
      {
        "height": 128,
        "url": "https://i.scdn.co/image/078c3d6784e53ca7490fb63218560d20100a18f2",
        "width": 200
      },
      {
        "height": 41,
        "url": "https://i.scdn.co/image/e7a6ecc704516f1bdc3ff67e96fb51435ebeebbb",
        "width": 64
      }
    ],
    "name": "The Police",
    "type": "artist",
    "uri": "spotify:artist:5NGO30tJxFlKixkPSgXcFE"
  },
  {
    "genres": [
      "rock en español",
      "latin rock",
      "argentine rock",
      "latin alternative"
    ],
    "href": "https://api.spotify.com/v1/artists/7An4yvF7hDYDolN4m5zKBp",
    "id": "7An4yvF7hDYDolN4m5zKBp",
    "images": [
      {
        "height": 640,
        "url": "https://i.scdn.co/image/ab6761610000e5ebe17b9f28e68b545e075ba35f",
        "width": 640
      },
      {
        "height": 320,
        "url": "https://i.scdn.co/image/ab67616100005174e17b9f28e68b545e075ba35f",
        "width": 320
      },
      {
        "height": 160,
        "url": "https://i.scdn.co/image/ab6761610000f178e17b9f28e68b545e075ba35f",
        "width": 160
      }
    ],
    "name": "Soda Stereo",
    "type": "artist",
    "uri": "spotify:artist:7An4yvF7hDYDolN4m5zKBp"
  },
  {
    "genres": [
      "reggaeton"
    ],
    "href": "https://api.spotify.com/v1/artists/0GM7qgcRCORpGnfcN2tCiB",
    "id": "0GM7qgcRCORpGnfcN2tCiB",
    "images": [
      {
        "height": 640,
        "url": "https://i.scdn.co/image/ab6761610000e5eba0d42a558309507a6a3b3311",
        "width": 640
      },
      {
        "height": 320,
        "url": "https://i.scdn.co/image/ab67616100005174a0d42a558309507a6a3b3311",
        "width": 320
      },
      {
        "height": 160,
        "url": "https://i.scdn.co/image/ab6761610000f178a0d42a558309507a6a3b3311",
        "width": 160
      }
    ],
    "name": "Tainy",
    "type": "artist",
    "uri": "spotify:artist:0GM7qgcRCORpGnfcN2tCiB"
  },
  {
    "genres": [
      "alternative rock"
    ],
    "href": "https://api.spotify.com/v1/artists/0C0XlULifJtAgn6ZNCW2eu",
    "id": "0C0XlULifJtAgn6ZNCW2eu",
    "images": [
      {
        "height": 640,
        "url": "https://i.scdn.co/image/ab6761610000e5eb207b21f3ed0ee96adce3166a",
        "width": 640
      },
      {
        "height": 320,
        "url": "https://i.scdn.co/image/ab67616100005174207b21f3ed0ee96adce3166a",
        "width": 320
      },
      {
        "height": 160,
        "url": "https://i.scdn.co/image/ab6761610000f178207b21f3ed0ee96adce3166a",
        "width": 160
      }
    ],
    "name": "The Killers",
    "type": "artist",
    "uri": "spotify:artist:0C0XlULifJtAgn6ZNCW2eu"
  },
  {
    "genres": [
      "neo-psychedelic",
      "indie"
    ],
    "href": "https://api.spotify.com/v1/artists/5INjqkS1o8h1imAzPqGZBb",
    "id": "5INjqkS1o8h1imAzPqGZBb",
    "images": [
      {
        "height": 640,
        "url": "https://i.scdn.co/image/ab6761610000e5ebe412a782245eb20d9626c601",
        "width": 640
      },
      {
        "height": 320,
        "url": "https://i.scdn.co/image/ab67616100005174e412a782245eb20d9626c601",
        "width": 320
      },
      {
        "height": 160,
        "url": "https://i.scdn.co/image/ab6761610000f178e412a782245eb20d9626c601",
        "width": 160
      }
    ],
    "name": "Tame Impala",
    "type": "artist",
    "uri": "spotify:artist:5INjqkS1o8h1imAzPqGZBb"
  },
  {
    "genres": [
      "indie",
      "indie rock"
    ],
    "href": "https://api.spotify.com/v1/artists/1GLtl8uqKmnyCWxHmw9tL4",
    "id": "1GLtl8uqKmnyCWxHmw9tL4",
    "images": [
      {
        "height": 640,
        "url": "https://i.scdn.co/image/ab6761610000e5ebdb445115fc89f2ede86dab8a",
        "width": 640
      },
      {
        "height": 320,
        "url": "https://i.scdn.co/image/ab67616100005174db445115fc89f2ede86dab8a",
        "width": 320
      },
      {
        "height": 160,
        "url": "https://i.scdn.co/image/ab6761610000f178db445115fc89f2ede86dab8a",
        "width": 160
      }
    ],
    "name": "The Kooks",
    "type": "artist",
    "uri": "spotify:artist:1GLtl8uqKmnyCWxHmw9tL4"
  },
  {
    "genres": [
      "rap"
    ],
    "href": "https://api.spotify.com/v1/artists/6l3HvQ5sa6mXTsMTB19rO5",
    "id": "6l3HvQ5sa6mXTsMTB19rO5",
    "images": [
      {
        "height": 640,
        "url": "https://i.scdn.co/image/ab6761610000e5eb4b053c29fd4b317ff825f0dc",
        "width": 640
      },
      {
        "height": 320,
        "url": "https://i.scdn.co/image/ab676161000051744b053c29fd4b317ff825f0dc",
        "width": 320
      },
      {
        "height": 160,
        "url": "https://i.scdn.co/image/ab6761610000f1784b053c29fd4b317ff825f0dc",
        "width": 160
      }
    ],
    "name": "J. Cole",
    "type": "artist",
    "uri": "spotify:artist:6l3HvQ5sa6mXTsMTB19rO5"
  }
]