[
  {
    "album": {
      "artists": [
        {
          "external_urls": {
            "spotify": "https://open.spotify.com/artist/0XNa1vTidXlvJ2gHSsRi4A"
          },
          "href": "https://api.spotify.com/v1/artists/0XNa1vTidXlvJ2gHSsRi4A",
          "id": "0XNa1vTidXlvJ2gHSsRi4A",
          "name": "Franz Ferdinand",
          "type": "artist",
          "uri": "spotify:artist:0XNa1vTidXlvJ2gHSsRi4A"
        }
      ],
      "href": "https://api.spotify.com/v1/albums/6ppF24fU5pqbPrPuK5zVnS",
      "images": [
        {
          "height": 640,
          "url": "https://i.scdn.co/image/ab67616d0000b273c3b34cc2e76e11b6b6e112e6",
          "width": 640
        },
        {
          "height": 300,
          "url": "https://i.scdn.co/image/ab67616d00001e02c3b34cc2e76e11b6b6e112e6",
          "width": 300
        },
        {
          "height": 64,
          "url": "https://i.scdn.co/image/ab67616d00004851c3b34cc2e76e11b6b6e112e6",
          "width": 64
        }
      ],
      "name": "Tonight",
      "release_date": "2009-01-27",
      "release_date_precision": "day",
      "total_tracks": 12,
      "type": "album",
      "uri": "spotify:album:6ppF24fU5pqbPrPuK5zVnS"
    },
    "artists": [
      {
        "external_urls": {
          "spotify": "https://open.spotify.com/artist/0XNa1vTidXlvJ2gHSsRi4A"
        },
        "href": "https://api.spotify.com/v1/artists/0XNa1vTidXlvJ2gHSsRi4A",
        "id": "0XNa1vTidXlvJ2gHSsRi4A",
        "name": "Franz Ferdinand",
        "type": "artist",
        "uri": "spotify:artist:0XNa1vTidXlvJ2gHSsRi4A"
      }
    ],
    "explicit": false,
    "href": "https://api.spotify.com/v1/tracks/4VP8QiCeaZq8BeTIUrMQOG",
    "is_local": false,
    "name": "No You Girls",
    "preview_url": null
  },
  {
    "album": {
      "artists": [
        {
          "external_urls": {
            "spotify": "https://open.spotify.com/artist/1xU878Z1QtBldR7ru9owdU"
          },
          "href": "https://api.spotify.com/v1/artists/1xU878Z1QtBldR7ru9owdU",
          "id": "1xU878Z1QtBldR7ru9owdU",
          "name": "Phoenix",
          "type": "artist",
          "uri": "spotify:artist:1xU878Z1QtBldR7ru9owdU"
        }
      ],
      "href": "https://api.spotify.com/v1/albums/7g4qoHjkYvfFkXJEZCjtc1",
      "images": [
        {
          "height": 640,
          "url": "https://i.scdn.co/image/ab67616d0000b27362cbc442278eefdde1a93efd",
          "width": 640
        },
        {
          "height": 300,
          "url": "https://i.scdn.co/image/ab67616d00001e0262cbc442278eefdde1a93efd",
          "width": 300
        },
        {
          "height": 64,
          "url": "https://i.scdn.co/image/ab67616d0000485162cbc442278eefdde1a93efd",
          "width": 64
        }
      ],
      "name": "Wolfgang Amadeus Phoenix",
      "release_date": "2009-05-25",
      "release_date_precision": "day",
      "total_tracks": 10,
      "type": "album",
      "uri": "spotify:album:7g4qoHjkYvfFkXJEZCjtc1"
    },
    "artists": [
      {
        "external_urls": {
          "spotify": "https://open.spotify.com/artist/1xU878Z1QtBldR7ru9owdU"
        },
        "href": "https://api.spotify.com/v1/artists/1xU878Z1QtBldR7ru9owdU",
        "id": "1xU878Z1QtBldR7ru9owdU",
        "name": "Phoenix",
        "type": "artist",
        "uri": "spotify:artist:1xU878Z1QtBldR7ru9owdU"
      }
    ],
    "explicit": false,
    "href": "https://api.spotify.com/v1/tracks/4esUVfYnFcCCVHntx9FQCb",
    "is_local": false,
    "name": "Lisztomania",
    "preview_url": null
  },
  {
    "album": {
      "artists": [
        {
          "external_urls": {
            "spotify": "https://open.spotify.com/artist/1xU878Z1QtBldR7ru9owdU"
          },
          "href": "https://api.spotify.com/v1/artists/1xU878Z1QtBldR7ru9owdU",
          "id": "1xU878Z1QtBldR7ru9owdU",
          "name": "Phoenix",
          "type": "artist",
          "uri": "spotify:artist:1xU878Z1QtBldR7ru9owdU"
        }
      ],
      "href": "https://api.spotify.com/v1/albums/7g4qoHjkYvfFkXJEZCjtc1",
      "images": [
        {
          "height": 640,
          "url": "https://i.scdn.co/image/ab67616d0000b27362cbc442278eefdde1a93efd",
          "width": 640
        },
        {
          "height": 300,
          "url": "https://i.scdn.co/image/ab67616d00001e0262cbc442278eefdde1a93efd",
          "width": 300
        },
        {
          "height": 64,
          "url": "https://i.scdn.co/image/ab67616d0000485162cbc442278eefdde1a93efd",
          "width": 64
        }
      ],
      "name": "Wolfgang Amadeus Phoenix",
      "release_date": "2009-05-25",
      "release_date_precision": "day",
      "total_tracks": 10,
      "type": "album",
      "uri": "spotify:album:7g4qoHjkYvfFkXJEZCjtc1"
    },
    "artists": [
      {
        "external_urls": {
          "spotify": "https://open.spotify.com/artist/1xU878Z1QtBldR7ru9owdU"
        },
        "href": "https://api.spotify.com/v1/artists/1xU878Z1QtBldR7ru9owdU",
        "id": "1xU878Z1QtBldR7ru9owdU",
        "name": "Phoenix",
        "type": "artist",
        "uri": "spotify:artist:1xU878Z1QtBldR7ru9owdU"
      }
    ],
    "explicit": false,
    "href": "https://api.spotify.com/v1/tracks/4esUVfYnFcCCVHntx9FQCb",
    "is_local": false,
    "name": "Lisztomania",
    "preview_url": null
  },
  {
    "album": {
      "artists": [
        {
          "external_urls": {
            "spotify": "https://open.spotify.com/artist/7MhMgCo0Bl0Kukl93PZbYS"
          },
          "href": "https://api.spotify.com/v1/artists/7MhMgCo0Bl0Kukl93PZbYS",
          "id": "7MhMgCo0Bl0Kukl93PZbYS",
          "name": "Blur",
          "type": "artist",
          "uri": "spotify:artist:7MhMgCo0Bl0Kukl93PZbYS"
        }
      ],
      "href": "https://api.spotify.com/v1/albums/7HvIrSkKGJCzd8AKyjTJ6Q",
      "images": [
        {
          "height": 640,
          "url": "https://i.scdn.co/image/ab67616d0000b273de114203356c1f7b136960b6",
          "width": 640
        },
        {
          "height": 300,
          "url": "https://i.scdn.co/image/ab67616d00001e02de114203356c1f7b136960b6",
          "width": 300
        },
        {
          "height": 64,
          "url": "https://i.scdn.co/image/ab67616d00004851de114203356c1f7b136960b6",
          "width": 64
        }
      ],
      "name": "Blur (Special Edition)",
      "release_date": "1997-02-10",
      "release_date_precision": "day",
      "total_tracks": 32,
      "type": "album",
      "uri": "spotify:album:7HvIrSkKGJCzd8AKyjTJ6Q"
    },
    "artists": [
      {
        "external_urls": {
          "spotify": "https://open.spotify.com/artist/7MhMgCo0Bl0Kukl93PZbYS"
        },
        "href": "https://api.spotify.com/v1/artists/7MhMgCo0Bl0Kukl93PZbYS",
        "id": "7MhMgCo0Bl0Kukl93PZbYS",
        "name": "Blur",
        "type": "artist",
        "uri": "spotify:artist:7MhMgCo0Bl0Kukl93PZbYS"
      }
    ],
    "explicit": false,
    "href": "https://api.spotify.com/v1/tracks/1FTSo4v6BOZH9QxKc3MbVM",
    "is_local": false,
    "name": "Song 2 - 2012 Remaster",
    "preview_url": null
  },
  {
    "album": {
      "artists": [
        {
          "external_urls": {
            "spotify": "https://open.spotify.com/artist/3TVXtAsR1Inumwj472S9r4"
          },
          "href": "https://api.spotify.com/v1/artists/3TVXtAsR1Inumwj472S9r4",
          "id": "3TVXtAsR1Inumwj472S9r4",
          "name": "Drake",
          "type": "artist",
          "uri": "spotify:artist:3TVXtAsR1Inumwj472S9r4"
        }
      ],
      "href": "https://api.spotify.com/v1/albums/1lXY618HWkwYKJWBRYR4MK",
      "images": [
        {
          "height": 640,
          "url": "https://i.scdn.co/image/ab67616d0000b2734f0fd9dad63977146e685700",
          "width": 640
        },
        {
          "height": 300,
          "url": "https://i.scdn.co/image/ab67616d00001e024f0fd9dad63977146e685700",
          "width": 300
        },
        {
          "height": 64,
          "url": "https://i.scdn.co/image/ab67616d000048514f0fd9dad63977146e685700",
          "width": 64
        }
      ],
      "name": "More Life",
      "release_date": "2017-03-18",
      "release_date_precision": "day",
      "total_tracks": 22,
      "type": "album",
      "uri": "spotify:album:1lXY618HWkwYKJWBRYR4MK"
    },
    "artists": [
      {
        "external_urls": {
          "spotify": "https://open.spotify.com/artist/3TVXtAsR1Inumwj472S9r4"
        },
        "href": "https://api.spotify.com/v1/artists/3TVXtAsR1Inumwj472S9r4",
        "id": "3TVXtAsR1Inumwj472S9r4",
        "name": "Drake",
        "type": "artist",
        "uri": "spotify:artist:3TVXtAsR1Inumwj472S9r4"
      }
    ],
    "explicit": true,
    "href": "https://api.spotify.com/v1/tracks/2KvHC9z14GSl4YpkNMX384",
    "is_local": false,
    "name": "Do Not Disturb",
    "preview_url": null
  },
  {
    "album": {
      "artists": [
        {
          "external_urls": {
            "spotify": "https://open.spotify.com/artist/3TVXtAsR1Inumwj472S9r4"
          },
          "href": "https://api.spotify.com/v1/artists/3TVXtAsR1Inumwj472S9r4",
          "id": "3TVXtAsR1Inumwj472S9r4",
          "name": "Drake",
          "type": "artist",
          "uri": "spotify:artist:3TVXtAsR1Inumwj472S9r4"
        },
        {
          "external_urls": {
            "spotify": "https://open.spotify.com/artist/1URnnhqYAYcrqrcwql10ft"
          },
          "href": "https://api.spotify.com/v1/artists/1URnnhqYAYcrqrcwql10ft",
          "id": "1URnnhqYAYcrqrcwql10ft",
          "name": "21 Savage",
          "type": "artist",
          "uri": "spotify:artist:1URnnhqYAYcrqrcwql10ft"
        }
      ],
      "href": "https://api.spotify.com/v1/albums/5MS3MvWHJ3lOZPLiMxzOU6",
      "images": [
        {
          "height": 640,
          "url": "https://i.scdn.co/image/ab67616d0000b27302854a7060fccc1a66a4b5ad",
          "width": 640
        },
        {
          "height": 300,
          "url": "https://i.scdn.co/image/ab67616d00001e0202854a7060fccc1a66a4b5ad",
          "width": 300
        },
        {
          "height": 64,
          "url": "https://i.scdn.co/image/ab67616d0000485102854a7060fccc1a66a4b5ad",
          "width": 64
        }
      ],
      "name": "Her Loss",
      "release_date": "2022-11-04",
      "release_date_precision": "day",
      "total_tracks": 16,
      "type": "album",
      "uri": "spotify:album:5MS3MvWHJ3lOZPLiMxzOU6"
    },
    "artists": [
      {
        "external_urls": {
          "spotify": "https://open.spotify.com/artist/3TVXtAsR1Inumwj472S9r4"
        },
        "href": "https://api.spotify.com/v1/artists/3TVXtAsR1Inumwj472S9r4",
        "id": "3TVXtAsR1Inumwj472S9r4",
        "name": "Drake",
        "type": "artist",
        "uri": "spotify:artist:3TVXtAsR1Inumwj472S9r4"
      },
      {
        "external_urls": {
          "spotify": "https://open.spotify.com/artist/1URnnhqYAYcrqrcwql10ft"
        },
        "href": "https://api.spotify.com/v1/artists/1URnnhqYAYcrqrcwql10ft",
        "id": "1URnnhqYAYcrqrcwql10ft",
        "name": "21 Savage",
        "type": "artist",
        "uri": "spotify:artist:1URnnhqYAYcrqrcwql10ft"
      }
    ],
    "explicit": true,
    "href": "https://api.spotify.com/v1/tracks/0sSRLXxknVTQDStgU1NqpY",
    "is_local": false,
    "name": "Hours In Silence",
    "preview_url": null
  },
  {
    "album": {
      "artists": [
        {
          "external_urls": {
            "spotify": "https://open.spotify.com/artist/3TVXtAsR1Inumwj472S9r4"
          },
          "href": "https://api.spotify.com/v1/artists/3TVXtAsR1Inumwj472S9r4",
          "id": "3TVXtAsR1Inumwj472S9r4",
          "name": "Drake",
          "type": "artist",
          "uri": "spotify:artist:3TVXtAsR1Inumwj472S9r4"
        }
      ],
      "href": "https://api.spotify.com/v1/albums/5mz0mJxb80gqJIcRf9LGHJ",
      "images": [
        {
          "height": 640,
          "url": "https://i.scdn.co/image/ab67616d0000b273a4dfa7122ec07fe3a1af22e7",
          "width": 640
        },
        {
          "height": 300,
          "url": "https://i.scdn.co/image/ab67616d00001e02a4dfa7122ec07fe3a1af22e7",
          "width": 300
        },
        {
          "height": 64,
          "url": "https://i.scdn.co/image/ab67616d00004851a4dfa7122ec07fe3a1af22e7",
          "width": 64
        }
      ],
      "name": "Nothing Was The Same (Deluxe)",
      "release_date": "2013-01-01",
      "release_date_precision": "day",
      "total_tracks": 15,
      "type": "album",
      "uri": "spotify:album:5mz0mJxb80gqJIcRf9LGHJ"
    },
    "artists": [
      {
        "external_urls": {
          "spotify": "https://open.spotify.com/artist/3TVXtAsR1Inumwj472S9r4"
        },
        "href": "https://api.spotify.com/v1/artists/3TVXtAsR1Inumwj472S9r4",
        "id": "3TVXtAsR1Inumwj472S9r4",
        "name": "Drake",
        "type": "artist",
        "uri": "spotify:artist:3TVXtAsR1Inumwj472S9r4"
      }
    ],
    "explicit": true,
    "href": "https://api.spotify.com/v1/tracks/3eN46sMTppXYMAyWi37wn1",
    "is_local": false,
    "name": "Come Thru",
    "preview_url": null
  },
  {
    "album": {
      "artists": [
        {
          "external_urls": {
            "spotify": "https://open.spotify.com/artist/3TVXtAsR1Inumwj472S9r4"
          },
          "href": "https://api.spotify.com/v1/artists/3TVXtAsR1Inumwj472S9r4",
          "id": "3TVXtAsR1Inumwj472S9r4",
          "name": "Drake",
          "type": "artist",
          "uri": "spotify:artist:3TVXtAsR1Inumwj472S9r4"
        },
        {
          "external_urls": {
            "spotify": "https://open.spotify.com/artist/1URnnhqYAYcrqrcwql10ft"
          },
          "href": "https://api.spotify.com/v1/artists/1URnnhqYAYcrqrcwql10ft",
          "id": "1URnnhqYAYcrqrcwql10ft",
          "name": "21 Savage",
          "type": "artist",
          "uri": "spotify:artist:1URnnhqYAYcrqrcwql10ft"
        }
      ],
      "href": "https://api.spotify.com/v1/albums/5MS3MvWHJ3lOZPLiMxzOU6",
      "images": [
        {
          "height": 640,
          "url": "https://i.scdn.co/image/ab67616d0000b27302854a7060fccc1a66a4b5ad",
          "width": 640
        },
        {
          "height": 300,
          "url": "https://i.scdn.co/image/ab67616d00001e0202854a7060fccc1a66a4b5ad",
          "width": 300
        },
        {
          "height": 64,
          "url": "https://i.scdn.co/image/ab67616d0000485102854a7060fccc1a66a4b5ad",
          "width": 64
        }
      ],
      "name": "Her Loss",
      "release_date": "2022-11-04",
      "release_date_precision": "day",
      "total_tracks": 16,
      "type": "album",
      "uri": "spotify:album:5MS3MvWHJ3lOZPLiMxzOU6"
    },
    "artists": [
      {
        "external_urls": {
          "spotify": "https://open.spotify.com/artist/3TVXtAsR1Inumwj472S9r4"
        },
        "href": "https://api.spotify.com/v1/artists/3TVXtAsR1Inumwj472S9r4",
        "id": "3TVXtAsR1Inumwj472S9r4",
        "name": "Drake",
        "type": "artist",
        "uri": "spotify:artist:3TVXtAsR1Inumwj472S9r4"
      },
      {
        "external_urls": {
          "spotify": "https://open.spotify.com/artist/1URnnhqYAYcrqrcwql10ft"
        },
        "href": "https://api.spotify.com/v1/artists/1URnnhqYAYcrqrcwql10ft",
        "id": "1URnnhqYAYcrqrcwql10ft",
        "name": "21 Savage",
        "type": "artist",
        "uri": "spotify:artist:1URnnhqYAYcrqrcwql10ft"
      }
    ],
    "explicit": true,
    "href": "https://api.spotify.com/v1/tracks/1bDbXMyjaUIooNwFE9wn0N",
    "is_local": false,
    "name": "Rich Flex",
    "preview_url": null
  },
  {
    "album": {
      "artists": [
        {
          "external_urls": {
            "spotify": "https://open.spotify.com/artist/3TVXtAsR1Inumwj472S9r4"
          },
          "href": "https://api.spotify.com/v1/artists/3TVXtAsR1Inumwj472S9r4",
          "id": "3TVXtAsR1Inumwj472S9r4",
          "name": "Drake",
          "type": "artist",
          "uri": "spotify:artist:3TVXtAsR1Inumwj472S9r4"
        }
      ],
      "href": "https://api.spotify.com/v1/albums/40GMAhriYJRO1rsY4YdrZb",
      "images": [
        {
          "height": 640,
          "url": "https://i.scdn.co/image/ab67616d0000b2739416ed64daf84936d89e671c",
          "width": 640
        },
        {
          "height": 300,
          "url": "https://i.scdn.co/image/ab67616d00001e029416ed64daf84936d89e671c",
          "width": 300
        },
        {
          "height": 64,
          "url": "https://i.scdn.co/image/ab67616d000048519416ed64daf84936d89e671c",
          "width": 64
        }
      ],
      "name": "Views",
      "release_date": "2016-05-06",
      "release_date_precision": "day",
      "total_tracks": 20,
      "type": "album",
      "uri": "spotify:album:40GMAhriYJRO1rsY4YdrZb"
    },
    "artists": [
      {
        "external_urls": {
          "spotify": "https://open.spotify.com/artist/3TVXtAsR1Inumwj472S9r4"
        },
        "href": "https://api.spotify.com/v1/artists/3TVXtAsR1Inumwj472S9r4",
        "id": "3TVXtAsR1Inumwj472S9r4",
        "name": "Drake",
        "type": "artist",
        "uri": "spotify:artist:3TVXtAsR1Inumwj472S9r4"
      }
    ],
    "explicit": false,
    "href": "https://api.spotify.com/v1/tracks/0wwPcA6wtMf6HUMpIRdeP7",
    "is_local": false,
    "name": "Hotline Bling",
    "preview_url": null
  },
  {
    "album": {
      "artists": [
        {
          "external_urls": {
            "spotify": "https://open.spotify.com/artist/3TVXtAsR1Inumwj472S9r4"
          },
          "href": "https://api.spotify.com/v1/artists/3TVXtAsR1Inumwj472S9r4",
          "id": "3TVXtAsR1Inumwj472S9r4",
          "name": "Drake",
          "type": "artist",
          "uri": "spotify:artist:3TVXtAsR1Inumwj472S9r4"
        }
      ],
      "href": "https://api.spotify.com/v1/albums/1XslIirSxfAhhxRdn4Li9t",
      "images": [
        {
          "height": 640,
          "url": "https://i.scdn.co/image/ab67616d0000b273a90d170c61fb7d063d47161d",
          "width": 640
        },
        {
          "height": 300,
          "url": "https://i.scdn.co/image/ab67616d00001e02a90d170c61fb7d063d47161d",
          "width": 300
        },
        {
          "height": 64,
          "url": "https://i.scdn.co/image/ab67616d00004851a90d170c61fb7d063d47161d",
          "width": 64
        }
      ],
      "name": "Nothing Was The Same",
      "release_date": "2013-01-01",
      "release_date_precision": "day",
      "total_tracks": 13,
      "type": "album",
      "uri": "spotify:album:1XslIirSxfAhhxRdn4Li9t"
    },
    "artists": [
      {
        "external_urls": {
          "spotify": "https://open.spotify.com/artist/3TVXtAsR1Inumwj472S9r4"
        },
        "href": "https://api.spotify.com/v1/artists/3TVXtAsR1Inumwj472S9r4",
        "id": "3TVXtAsR1Inumwj472S9r4",
        "name": "Drake",
        "type": "artist",
        "uri": "spotify:artist:3TVXtAsR1Inumwj472S9r4"
      },
      {
        "external_urls": {
          "spotify": "https://open.spotify.com/artist/4HzKw8XcD0piJmDrrPRCYk"
        },
        "href": "https://api.spotify.com/v1/artists/4HzKw8XcD0piJmDrrPRCYk",
        "id": "4HzKw8XcD0piJmDrrPRCYk",
        "name": "Majid Jordan",
        "type": "artist",
        "uri": "spotify:artist:4HzKw8XcD0piJmDrrPRCYk"
      }
    ],
    "explicit": false,
    "href": "https://api.spotify.com/v1/tracks/2aSC2xhRxOLiiZZVjhbylH",
    "is_local": false,
    "name": "Hold On, We're Going Home",
    "preview_url": null
  },
  {
    "album": {
      "artists": [
        {
          "external_urls": {
            "spotify": "https://open.spotify.com/artist/3TVXtAsR1Inumwj472S9r4"
          },
          "href": "https://api.spotify.com/v1/artists/3TVXtAsR1Inumwj472S9r4",
          "id": "3TVXtAsR1Inumwj472S9r4",
          "name": "Drake",
          "type": "artist",
          "uri": "spotify:artist:3TVXtAsR1Inumwj472S9r4"
        }
      ],
      "href": "https://api.spotify.com/v1/albums/4Q7cRXio6mF2ImVUCcezPO",
      "images": [
        {
          "height": 640,
          "url": "https://i.scdn.co/image/ab67616d0000b273e286ee36b4015afa8832356a",
          "width": 640
        },
        {
          "height": 300,
          "url": "https://i.scdn.co/image/ab67616d00001e02e286ee36b4015afa8832356a",
          "width": 300
        },
        {
          "height": 64,
          "url": "https://i.scdn.co/image/ab67616d00004851e286ee36b4015afa8832356a",
          "width": 64
        }
      ],
      "name": "For All The Dogs Scary Hours Edition",
      "release_date": "2023-11-17",
      "release_date_precision": "day",
      "total_tracks": 29,
      "type": "album",
      "uri": "spotify:album:4Q7cRXio6mF2ImVUCcezPO"
    },
    "artists": [
      {
        "external_urls": {
          "spotify": "https://open.spotify.com/artist/3TVXtAsR1Inumwj472S9r4"
        },
        "href": "https://api.spotify.com/v1/artists/3TVXtAsR1Inumwj472S9r4",
        "id": "3TVXtAsR1Inumwj472S9r4",
        "name": "Drake",
        "type": "artist",
        "uri": "spotify:artist:3TVXtAsR1Inumwj472S9r4"
      }
    ],
    "explicit": true,
    "href": "https://api.spotify.com/v1/tracks/5Mc8XDfGQCMkOEZm9rS1cE",
    "is_local": false,
    "name": "Red Button",
    "preview_url": null
  },
  {
    "album": {
      "artists": [
        {
          "external_urls": {
            "spotify": "https://open.spotify.com/artist/3TVXtAsR1Inumwj472S9r4"
          },
          "href": "https://api.spotify.com/v1/artists/3TVXtAsR1Inumwj472S9r4",
          "id": "3TVXtAsR1Inumwj472S9r4",
          "name": "Drake",
          "type": "artist",
          "uri": "spotify:artist:3TVXtAsR1Inumwj472S9r4"
        }
      ],
      "href": "https://api.spotify.com/v1/albums/0ptlfJfwGTy0Yvrk14JK1I",
      "images": [
        {
          "height": 640,
          "url": "https://i.scdn.co/image/ab67616d0000b2732090f4f6cc406e6d3c306733",
          "width": 640
        },
        {
          "height": 300,
          "url": "https://i.scdn.co/image/ab67616d00001e022090f4f6cc406e6d3c306733",
          "width": 300
        },
        {
          "height": 64,
          "url": "https://i.scdn.co/image/ab67616d000048512090f4f6cc406e6d3c306733",
          "width": 64
        }
      ],
      "name": "If You're Reading This It's Too Late",
      "release_date": "2015-02-12",
      "release_date_precision": "day",
      "total_tracks": 17,
      "type": "album",
      "uri": "spotify:album:0ptlfJfwGTy0Yvrk14JK1I"
    },
    "artists": [
      {
        "external_urls": {
          "spotify": "https://open.spotify.com/artist/3TVXtAsR1Inumwj472S9r4"
        },
        "href": "https://api.spotify.com/v1/artists/3TVXtAsR1Inumwj472S9r4",
        "id": "3TVXtAsR1Inumwj472S9r4",
        "name": "Drake",
        "type": "artist",
        "uri": "spotify:artist:3TVXtAsR1Inumwj472S9r4"
      },
      {
        "external_urls": {
          "spotify": "https://open.spotify.com/artist/2HPaUgqeutzr3jx5a9WyDV"
        },
        "href": "https://api.spotify.com/v1/artists/2HPaUgqeutzr3jx5a9WyDV",
        "id": "2HPaUgqeutzr3jx5a9WyDV",
        "name": "PARTYNEXTDOOR",
        "type": "artist",
        "uri": "spotify:artist:2HPaUgqeutzr3jx5a9WyDV"
      }
    ],
    "explicit": true,
    "href": "https://api.spotify.com/v1/tracks/1OHoBC4icbuNhpSxP400sv",
    "is_local": false,
    "name": "Preach",
    "preview_url": null
  },
  {
    "album": {
      "artists": [
        {
          "external_urls": {
            "spotify": "https://open.spotify.com/artist/3TVXtAsR1Inumwj472S9r4"
          },
          "href": "https://api.spotify.com/v1/artists/3TVXtAsR1Inumwj472S9r4",
          "id": "3TVXtAsR1Inumwj472S9r4",
          "name": "Drake",
          "type": "artist",
          "uri": "spotify:artist:3TVXtAsR1Inumwj472S9r4"
        }
      ],
      "href": "https://api.spotify.com/v1/albums/00HZxSA1sOS9T3nA950sg4",
      "images": [
        {
          "height": 640,
          "url": "https://i.scdn.co/image/ab67616d0000b2733f3b653b0a7b9e889a712c3d",
          "width": 640
        },
        {
          "height": 300,
          "url": "https://i.scdn.co/image/ab67616d00001e023f3b653b0a7b9e889a712c3d",
          "width": 300
        },
        {
          "height": 64,
          "url": "https://i.scdn.co/image/ab67616d000048513f3b653b0a7b9e889a712c3d",
          "width": 64
        }
      ],
      "name": "The Best In The World Pack",
      "release_date": "2019-06-15",
      "release_date_precision": "day",
      "total_tracks": 2,
      "type": "album",
      "uri": "spotify:album:00HZxSA1sOS9T3nA950sg4"
    },
    "artists": [
      {
        "external_urls": {
          "spotify": "https://open.spotify.com/artist/3TVXtAsR1Inumwj472S9r4"
        },
        "href": "https://api.spotify.com/v1/artists/3TVXtAsR1Inumwj472S9r4",
        "id": "3TVXtAsR1Inumwj472S9r4",
        "name": "Drake",
        "type": "artist",
        "uri": "spotify:artist:3TVXtAsR1Inumwj472S9r4"
      },
      {
        "external_urls": {
          "spotify": "https://open.spotify.com/artist/1sBkRIssrMs1AbVkOJbc7a"
        },
        "href": "https://api.spotify.com/v1/artists/1sBkRIssrMs1AbVkOJbc7a",
        "id": "1sBkRIssrMs1AbVkOJbc7a",
        "name": "Rick Ross",
        "type": "artist",
        "uri": "spotify:artist:1sBkRIssrMs1AbVkOJbc7a"
      }
    ],
    "explicit": true,
    "href": "https://api.spotify.com/v1/tracks/5ry2OE6R2zPQFDO85XkgRb",
    "is_local": false,
    "name": "Money In The Grave (Drake ft. Rick Ross)",
    "preview_url": null
  },
  {
    "album": {
      "artists": [
        {
          "external_urls": {
            "spotify": "https://open.spotify.com/artist/3aGFCoR8xGN6DKwvdzeSja"
          },
          "href": "https://api.spotify.com/v1/artists/3aGFCoR8xGN6DKwvdzeSja",
          "id": "3aGFCoR8xGN6DKwvdzeSja",
          "name": "ILOVEMAKONNEN",
          "type": "artist",
          "uri": "spotify:artist:3aGFCoR8xGN6DKwvdzeSja"
        }
      ],
      "href": "https://api.spotify.com/v1/albums/7dQR4QAB01LGWs1ExCiuD1",
      "images": [
        {
          "height": 640,
          "url": "https://i.scdn.co/image/ab67616d0000b273280f46fb75bd6358488504cc",
          "width": 640
        },
        {
          "height": 300,
          "url": "https://i.scdn.co/image/ab67616d00001e02280f46fb75bd6358488504cc",
          "width": 300
        },
        {
          "height": 64,
          "url": "https://i.scdn.co/image/ab67616d00004851280f46fb75bd6358488504cc",
          "width": 64
        }
      ],
      "name": "Tuesday (feat. Drake)",
      "release_date": "2014-09-01",
      "release_date_precision": "day",
      "total_tracks": 1,
      "type": "album",
      "uri": "spotify:album:7dQR4QAB01LGWs1ExCiuD1"
    },
    "artists": [
      {
        "external_urls": {
          "spotify": "https://open.spotify.com/artist/3aGFCoR8xGN6DKwvdzeSja"
        },
        "href": "https://api.spotify.com/v1/artists/3aGFCoR8xGN6DKwvdzeSja",
        "id": "3aGFCoR8xGN6DKwvdzeSja",
        "name": "ILOVEMAKONNEN",
        "type": "artist",
        "uri": "spotify:artist:3aGFCoR8xGN6DKwvdzeSja"
      },
      {
        "external_urls": {
          "spotify": "https://open.spotify.com/artist/3TVXtAsR1Inumwj472S9r4"
        },
        "href": "https://api.spotify.com/v1/artists/3TVXtAsR1Inumwj472S9r4",
        "id": "3TVXtAsR1Inumwj472S9r4",
        "name": "Drake",
        "type": "artist",
        "uri": "spotify:artist:3TVXtAsR1Inumwj472S9r4"
      }
    ],
    "explicit": true,
    "href": "https://api.spotify.com/v1/tracks/0nfR40ozDbrAhJndY4ybqH",
    "is_local": false,
    "name": "Tuesday (feat. Drake)",
    "preview_url": null
  },
  {
    "album": {
      "artists": [
        {
          "external_urls": {
            "spotify": "https://open.spotify.com/artist/3TVXtAsR1Inumwj472S9r4"
          },
          "href": "https://api.spotify.com/v1/artists/3TVXtAsR1Inumwj472S9r4",
          "id": "3TVXtAsR1Inumwj472S9r4",
          "name": "Drake",
          "type": "artist",
          "uri": "spotify:artist:3TVXtAsR1Inumwj472S9r4"
        }
      ],
      "href": "https://api.spotify.com/v1/albums/06me0leRR3AuF4IFiEytml",
      "images": [
        {
          "height": 640,
          "url": "https://i.scdn.co/image/ab67616d0000b27384bfd0d363f0179ac7c97fa5",
          "width": 640
        },
        {
          "height": 300,
          "url": "https://i.scdn.co/image/ab67616d00001e0284bfd0d363f0179ac7c97fa5",
          "width": 300
        },
        {
          "height": 64,
          "url": "https://i.scdn.co/image/ab67616d0000485184bfd0d363f0179ac7c97fa5",
          "width": 64
        }
      ],
      "name": "Push Ups",
      "release_date": "2024-04-19",
      "release_date_precision": "day",
      "total_tracks": 1,
      "type": "album",
      "uri": "spotify:album:06me0leRR3AuF4IFiEytml"
    },
    "artists": [
      {
        "external_urls": {
          "spotify": "https://open.spotify.com/artist/3TVXtAsR1Inumwj472S9r4"
        },
        "href": "https://api.spotify.com/v1/artists/3TVXtAsR1Inumwj472S9r4",
        "id": "3TVXtAsR1Inumwj472S9r4",
        "name": "Drake",
        "type": "artist",
        "uri": "spotify:artist:3TVXtAsR1Inumwj472S9r4"
      }
    ],
    "explicit": true,
    "href": "https://api.spotify.com/v1/tracks/3eh51r6rFWAlGQRlHx9QnQ",
    "is_local": false,
    "name": "Push Ups",
    "preview_url": null
  },
  {
    "album": {
      "artists": [
        {
          "external_urls": {
            "spotify": "https://open.spotify.com/artist/3TVXtAsR1Inumwj472S9r4"
          },
          "href": "https://api.spotify.com/v1/artists/3TVXtAsR1Inumwj472S9r4",
          "id": "3TVXtAsR1Inumwj472S9r4",
          "name": "Drake",
          "type": "artist",
          "uri": "spotify:artist:3TVXtAsR1Inumwj472S9r4"
        },
        {
          "external_urls": {
            "spotify": "https://open.spotify.com/artist/1RyvyyTE3xzB2ZywiAwp0i"
          },
          "href": "https://api.spotify.com/v1/artists/1RyvyyTE3xzB2ZywiAwp0i",
          "id": "1RyvyyTE3xzB2ZywiAwp0i",
          "name": "Future",
          "type": "artist",
          "uri": "spotify:artist:1RyvyyTE3xzB2ZywiAwp0i"
        }
      ],
      "href": "https://api.spotify.com/v1/albums/1ozpmkWcCHwsQ4QTnxOOdT",
      "images": [
        {
          "height": 640,
          "url": "https://i.scdn.co/image/ab67616d0000b273d6adfbd3f091d6f2b9af6507",
          "width": 640
        },
        {
          "height": 300,
          "url": "https://i.scdn.co/image/ab67616d00001e02d6adfbd3f091d6f2b9af6507",
          "width": 300
        },
        {
          "height": 64,
          "url": "https://i.scdn.co/image/ab67616d00004851d6adfbd3f091d6f2b9af6507",
          "width": 64
        }
      ],
      "name": "What A Time To Be Alive",
      "release_date": "2015-09-20",
      "release_date_precision": "day",
      "total_tracks": 11,
      "type": "album",
      "uri": "spotify:album:1ozpmkWcCHwsQ4QTnxOOdT"
    },
    "artists": [
      {
        "external_urls": {
          "spotify": "https://open.spotify.com/artist/3TVXtAsR1Inumwj472S9r4"
        },
        "href": "https://api.spotify.com/v1/artists/3TVXtAsR1Inumwj472S9r4",
        "id": "3TVXtAsR1Inumwj472S9r4",
        "name": "Drake",
        "type": "artist",
        "uri": "spotify:artist:3TVXtAsR1Inumwj472S9r4"
      },
      {
        "external_urls": {
          "spotify": "https://open.spotify.com/artist/1RyvyyTE3xzB2ZywiAwp0i"
        },
        "href": "https://api.spotify.com/v1/artists/1RyvyyTE3xzB2ZywiAwp0i",
        "id": "1RyvyyTE3xzB2ZywiAwp0i",
        "name": "Future",
        "type": "artist",
        "uri": "spotify:artist:1RyvyyTE3xzB2ZywiAwp0i"
      }
    ],
    "explicit": true,
    "href": "https://api.spotify.com/v1/tracks/0GR7iJLhj80KD5LkA14ZRn",
    "is_local": false,
    "name": "Digital Dash",
    "preview_url": null
  },
  {
    "album": {
      "artists": [
        {
          "external_urls": {
            "spotify": "https://open.spotify.com/artist/3TVXtAsR1Inumwj472S9r4"
          },
          "href": "https://api.spotify.com/v1/artists/3TVXtAsR1Inumwj472S9r4",
          "id": "3TVXtAsR1Inumwj472S9r4",
          "name": "Drake",
          "type": "artist",
          "uri": "spotify:artist:3TVXtAsR1Inumwj472S9r4"
        },
        {
          "external_urls": {
            "spotify": "https://open.spotify.com/artist/1URnnhqYAYcrqrcwql10ft"
          },
          "href": "https://api.spotify.com/v1/artists/1URnnhqYAYcrqrcwql10ft",
          "id": "1URnnhqYAYcrqrcwql10ft",
          "name": "21 Savage",
          "type": "artist",
          "uri": "spotify:artist:1URnnhqYAYcrqrcwql10ft"
        }
      ],
      "href": "https://api.spotify.com/v1/albums/5MS3MvWHJ3lOZPLiMxzOU6",
      "images": [
        {
          "height": 640,
          "url": "https://i.scdn.co/image/ab67616d0000b27302854a7060fccc1a66a4b5ad",
          "width": 640
        },
        {
          "height": 300,
          "url": "https://i.scdn.co/image/ab67616d00001e0202854a7060fccc1a66a4b5ad",
          "width": 300
        },
        {
          "height": 64,
          "url": "https://i.scdn.co/image/ab67616d0000485102854a7060fccc1a66a4b5ad",
          "width": 64
        }
      ],
      "name": "Her Loss",
      "release_date": "2022-11-04",
      "release_date_precision": "day",
      "total_tracks": 16,
      "type": "album",
      "uri": "spotify:album:5MS3MvWHJ3lOZPLiMxzOU6"
    },
    "artists": [
      {
        "external_urls": {
          "spotify": "https://open.spotify.com/artist/3TVXtAsR1Inumwj472S9r4"
        },
        "href": "https://api.spotify.com/v1/artists/3TVXtAsR1Inumwj472S9r4",
        "id": "3TVXtAsR1Inumwj472S9r4",
        "name": "Drake",
        "type": "artist",
        "uri": "spotify:artist:3TVXtAsR1Inumwj472S9r4"
      }
    ],
    "explicit": true,
    "href": "https://api.spotify.com/v1/tracks/0wshkEEcJUQU33RSRBb5dv",
    "is_local": false,
    "name": "BackOutsideBoyz",
    "preview_url": null
  },
  {
    "album": {
      "artists": [
        {
          "external_urls": {
            "spotify": "https://open.spotify.com/artist/3TVXtAsR1Inumwj472S9r4"
          },
          "href": "https://api.spotify.com/v1/artists/3TVXtAsR1Inumwj472S9r4",
          "id": "3TVXtAsR1Inumwj472S9r4",
          "name": "Drake",
          "type": "artist",
          "uri": "spotify:artist:3TVXtAsR1Inumwj472S9r4"
        }
      ],
      "href": "https://api.spotify.com/v1/albums/4czdORdCWP9umpbhFXK2fW",
      "images": [
        {
          "height": 640,
          "url": "https://i.scdn.co/image/ab67616d0000b2737d384516b23347e92a587ed1",
          "width": 640
        },
        {
          "height": 300,
          "url": "https://i.scdn.co/image/ab67616d00001e027d384516b23347e92a587ed1",
          "width": 300
        },
        {
          "height": 64,
          "url": "https://i.scdn.co/image/ab67616d000048517d384516b23347e92a587ed1",
          "width": 64
        }
      ],
      "name": "For All The Dogs",
      "release_date": "2023-10-06",
      "release_date_precision": "day",
      "total_tracks": 23,
      "type": "album",
      "uri": "spotify:album:4czdORdCWP9umpbhFXK2fW"
    },
    "artists": [
      {
        "external_urls": {
          "spotify": "https://open.spotify.com/artist/3TVXtAsR1Inumwj472S9r4"
        },
        "href": "https://api.spotify.com/v1/artists/3TVXtAsR1Inumwj472S9r4",
        "id": "3TVXtAsR1Inumwj472S9r4",
        "name": "Drake",
        "type": "artist",
        "uri": "spotify:artist:3TVXtAsR1Inumwj472S9r4"
      },
      {
        "external_urls": {
          "spotify": "https://open.spotify.com/artist/6l3HvQ5sa6mXTsMTB19rO5"
        },
        "href": "https://api.spotify.com/v1/artists/6l3HvQ5sa6mXTsMTB19rO5",
        "id": "6l3HvQ5sa6mXTsMTB19rO5",
        "name": "J. Cole",
        "type": "artist",
        "uri": "spotify:artist:6l3HvQ5sa6mXTsMTB19rO5"
      }
    ],
    "explicit": true,
    "href": "https://api.spotify.com/v1/tracks/7aqfrAY2p9BUSiupwk3svU",
    "is_local": false,
    "name": "First Person Shooter (feat. J. Cole)",
    "preview_url": null
  },
  {
    "album": {
      "artists": [
        {
          "external_urls": {
            "spotify": "https://open.spotify.com/artist/3TVXtAsR1Inumwj472S9r4"
          },
          "href": "https://api.spotify.com/v1/artists/3TVXtAsR1Inumwj472S9r4",
          "id": "3TVXtAsR1Inumwj472S9r4",
          "name": "Drake",
          "type": "artist",
          "uri": "spotify:artist:3TVXtAsR1Inumwj472S9r4"
        }
      ],
      "href": "https://api.spotify.com/v1/albums/4Q7cRXio6mF2ImVUCcezPO",
      "images": [
        {
          "height": 640,
          "url": "https://i.scdn.co/image/ab67616d0000b273e286ee36b4015afa8832356a",
          "width": 640
        },
        {
          "height": 300,
          "url": "https://i.scdn.co/image/ab67616d00001e02e286ee36b4015afa8832356a",
          "width": 300
        },
        {
          "height": 64,
          "url": "https://i.scdn.co/image/ab67616d00004851e286ee36b4015afa8832356a",
          "width": 64
        }
      ],
      "name": "For All The Dogs Scary Hours Edition",
      "release_date": "2023-11-17",
      "release_date_precision": "day",
      "total_tracks": 29,
      "type": "album",
      "uri": "spotify:album:4Q7cRXio6mF2ImVUCcezPO"
    },
    "artists": [
      {
        "external_urls": {
          "spotify": "https://open.spotify.com/artist/3TVXtAsR1Inumwj472S9r4"
        },
        "href": "https://api.spotify.com/v1/artists/3TVXtAsR1Inumwj472S9r4",
        "id": "3TVXtAsR1Inumwj472S9r4",
        "name": "Drake",
        "type": "artist",
        "uri": "spotify:artist:3TVXtAsR1Inumwj472S9r4"
      }
    ],
    "explicit": true,
    "href": "https://api.spotify.com/v1/tracks/1dKXBUKx7oCB2UXlkihNn8",
    "is_local": false,
    "name": "8am in Charlotte",
    "preview_url": null
  },
  {
    "album": {
      "artists": [
        {
          "external_urls": {
            "spotify": "https://open.spotify.com/artist/3TVXtAsR1Inumwj472S9r4"
          },
          "href": "https://api.spotify.com/v1/artists/3TVXtAsR1Inumwj472S9r4",
          "id": "3TVXtAsR1Inumwj472S9r4",
          "name": "Drake",
          "type": "artist",
          "uri": "spotify:artist:3TVXtAsR1Inumwj472S9r4"
        }
      ],
      "href": "https://api.spotify.com/v1/albums/1XslIirSxfAhhxRdn4Li9t",
      "images": [
        {
          "height": 640,
          "url": "https://i.scdn.co/image/ab67616d0000b273a90d170c61fb7d063d47161d",
          "width": 640
        },
        {
          "height": 300,
          "url": "https://i.scdn.co/image/ab67616d00001e02a90d170c61fb7d063d47161d",
          "width": 300
        },
        {
          "height": 64,
          "url": "https://i.scdn.co/image/ab67616d00004851a90d170c61fb7d063d47161d",
          "width": 64
        }
      ],
      "name": "Nothing Was The Same",
      "release_date": "2013-01-01",
      "release_date_precision": "day",
      "total_tracks": 13,
      "type": "album",
      "uri": "spotify:album:1XslIirSxfAhhxRdn4Li9t"
    },
    "artists": [
      {
        "external_urls": {
          "spotify": "https://open.spotify.com/artist/3TVXtAsR1Inumwj472S9r4"
        },
        "href": "https://api.spotify.com/v1/artists/3TVXtAsR1Inumwj472S9r4",
        "id": "3TVXtAsR1Inumwj472S9r4",
        "name": "Drake",
        "type": "artist",
        "uri": "spotify:artist:3TVXtAsR1Inumwj472S9r4"
      }
    ],
    "explicit": true,
    "href": "https://api.spotify.com/v1/tracks/5DI9jxTHrEiFAhStG7VA8E",
    "is_local": false,
    "name": "Started From the Bottom",
    "preview_url": null
  }
]