[
  {
    "album": {
      "artists": [
        {
          "external_urls": {
            "spotify": "https://open.spotify.com/artist/5Igpc9iLZ3YGtKeYfSrrOE"
          },
          "href": "https://api.spotify.com/v1/artists/5Igpc9iLZ3YGtKeYfSrrOE",
          "id": "5Igpc9iLZ3YGtKeYfSrrOE",
          "name": "Chris Lake",
          "type": "artist",
          "uri": "spotify:artist:5Igpc9iLZ3YGtKeYfSrrOE"
        }
      ],
      "href": "https://api.spotify.com/v1/albums/3DmcV2cmZdX9olNRHcRUZ2",
      "images": [
        {
          "height": 640,
          "url": "https://i.scdn.co/image/ab67616d0000b273eef1231340b1f14dde4816f0",
          "width": 640
        },
        {
          "height": 300,
          "url": "https://i.scdn.co/image/ab67616d00001e02eef1231340b1f14dde4816f0",
          "width": 300
        },
        {
          "height": 64,
          "url": "https://i.scdn.co/image/ab67616d00004851eef1231340b1f14dde4816f0",
          "width": 64
        }
      ],
      "name": "Chemistry",
      "release_date": "2025-07-11",
      "release_date_precision": "day",
      "total_tracks": 15,
      "type": "album",
      "uri": "spotify:album:3DmcV2cmZdX9olNRHcRUZ2"
    },
    "artists": [
      {
        "external_urls": {
          "spotify": "https://open.spotify.com/artist/5Igpc9iLZ3YGtKeYfSrrOE"
        },
        "href": "https://api.spotify.com/v1/artists/5Igpc9iLZ3YGtKeYfSrrOE",
        "id": "5Igpc9iLZ3YGtKeYfSrrOE",
        "name": "Chris Lake",
        "type": "artist",
        "uri": "spotify:artist:5Igpc9iLZ3YGtKeYfSrrOE"
      },
      {
        "external_urls": {
          "spotify": "https://open.spotify.com/artist/0jqbEIAvdjUOi5Za48pzQG"
        },
        "href": "https://api.spotify.com/v1/artists/0jqbEIAvdjUOi5Za48pzQG",
        "id": "0jqbEIAvdjUOi5Za48pzQG",
        "name": "Abel Balder",
        "type": "artist",
        "uri": "spotify:artist:0jqbEIAvdjUOi5Za48pzQG"
      }
    ],
    "explicit": false,
    "href": "https://api.spotify.com/v1/tracks/0zVYrhlpgLHLqnEtv38Fko",
    "is_local": false,
    "name": "Ease My Mind",
    "preview_url": null
  },
  {
    "album": {
      "artists": [
        {
          "external_urls": {
            "spotify": "https://open.spotify.com/artist/7kNqXtgeIwFtelmRjWv205"
          },
          "href": "https://api.spotify.com/v1/artists/7kNqXtgeIwFtelmRjWv205",
          "id": "7kNqXtgeIwFtelmRjWv205",
          "name": "John Summit",
          "type": "artist",
          "uri": "spotify:artist:7kNqXtgeIwFtelmRjWv205"
        },
        {
          "external_urls": {
            "spotify": "https://open.spotify.com/artist/7y5xCKz1V2iSh1YsOLyOPH"
          },
          "href": "https://api.spotify.com/v1/artists/7y5xCKz1V2iSh1YsOLyOPH",
          "id": "7y5xCKz1V2iSh1YsOLyOPH",
          "name": "Parachute Youth",
          "type": "artist",
          "uri": "spotify:artist:7y5xCKz1V2iSh1YsOLyOPH"
        }
      ],
      "href": "https://api.spotify.com/v1/albums/6GbUYC6kB63fND2yunOVmZ",
      "images": [
        {
          "height": 640,
          "url": "https://i.scdn.co/image/ab67616d0000b2739a4c8d615cea2603a14fa130",
          "width": 640
        },
        {
          "height": 300,
          "url": "https://i.scdn.co/image/ab67616d00001e029a4c8d615cea2603a14fa130",
          "width": 300
        },
        {
          "height": 64,
          "url": "https://i.scdn.co/image/ab67616d000048519a4c8d615cea2603a14fa130",
          "width": 64
        }
      ],
      "name": "Better Than This",
      "release_date": "2021-05-28",
      "release_date_precision": "day",
      "total_tracks": 2,
      "type": "album",
      "uri": "spotify:album:6GbUYC6kB63fND2yunOVmZ"
    },
    "artists": [
      {
        "external_urls": {
          "spotify": "https://open.spotify.com/artist/7kNqXtgeIwFtelmRjWv205"
        },
        "href": "https://api.spotify.com/v1/artists/7kNqXtgeIwFtelmRjWv205",
        "id": "7kNqXtgeIwFtelmRjWv205",
        "name": "John Summit",
        "type": "artist",
        "uri": "spotify:artist:7kNqXtgeIwFtelmRjWv205"
      },
      {
        "external_urls": {
          "spotify": "https://open.spotify.com/artist/7y5xCKz1V2iSh1YsOLyOPH"
        },
        "href": "https://api.spotify.com/v1/artists/7y5xCKz1V2iSh1YsOLyOPH",
        "id": "7y5xCKz1V2iSh1YsOLyOPH",
        "name": "Parachute Youth",
        "type": "artist",
        "uri": "spotify:artist:7y5xCKz1V2iSh1YsOLyOPH"
      }
    ],
    "explicit": false,
    "href": "https://api.spotify.com/v1/tracks/5OLSGox6JVpAyEQuoSYRcs",
    "is_local": false,
    "name": "Better Than This",
    "preview_url": null
  },
  {
    "album": {
      "artists": [
        {
          "external_urls": {
            "spotify": "https://open.spotify.com/artist/7tm9Tuc70geXOOyKhtZHIj"
          },
          "href": "https://api.spotify.com/v1/artists/7tm9Tuc70geXOOyKhtZHIj",
          "id": "7tm9Tuc70geXOOyKhtZHIj",
          "name": "Chris Lorenzo",
          "type": "artist",
          "uri": "spotify:artist:7tm9Tuc70geXOOyKhtZHIj"
        }
      ],
      "href": "https://api.spotify.com/v1/albums/4Fl1XT8Lr22cm10MW82DkF",
      "images": [
        {
          "height": 640,
          "url": "https://i.scdn.co/image/ab67616d0000b27389ce327086cedb300a3af32d",
          "width": 640
        },
        {
          "height": 300,
          "url": "https://i.scdn.co/image/ab67616d00001e0289ce327086cedb300a3af32d",
          "width": 300
        },
        {
          "height": 64,
          "url": "https://i.scdn.co/image/ab67616d0000485189ce327086cedb300a3af32d",
          "width": 64
        }
      ],
      "name": "Late Checkout",
      "release_date": "2019-10-11",
      "release_date_precision": "day",
      "total_tracks": 12,
      "type": "album",
      "uri": "spotify:album:4Fl1XT8Lr22cm10MW82DkF"
    },
    "artists": [
      {
        "external_urls": {
          "spotify": "https://open.spotify.com/artist/7tm9Tuc70geXOOyKhtZHIj"
        },
        "href": "https://api.spotify.com/v1/artists/7tm9Tuc70geXOOyKhtZHIj",
        "id": "7tm9Tuc70geXOOyKhtZHIj",
        "name": "Chris Lorenzo",
        "type": "artist",
        "uri": "spotify:artist:7tm9Tuc70geXOOyKhtZHIj"
      }
    ],
    "explicit": false,
    "href": "https://api.spotify.com/v1/tracks/5Zx3Uh6dGIVHWGUlWGnSlb",
    "is_local": false,
    "name": "Every Morning",
    "preview_url": null
  },
  {
    "album": {
      "artists": [
        {
          "external_urls": {
            "spotify": "https://open.spotify.com/artist/4p5WgeiPSPpqPDs7T6OkWf"
          },
          "href": "https://api.spotify.com/v1/artists/4p5WgeiPSPpqPDs7T6OkWf",
          "id": "4p5WgeiPSPpqPDs7T6OkWf",
          "name": "ANOTR",
          "type": "artist",
          "uri": "spotify:artist:4p5WgeiPSPpqPDs7T6OkWf"
        },
        {
          "external_urls": {
            "spotify": "https://open.spotify.com/artist/4f44GWlEQdXaWl8gQ9sPBC"
          },
          "href": "https://api.spotify.com/v1/artists/4f44GWlEQdXaWl8gQ9sPBC",
          "id": "4f44GWlEQdXaWl8gQ9sPBC",
          "name": "WAYNE SNOW",
          "type": "artist",
          "uri": "spotify:artist:4f44GWlEQdXaWl8gQ9sPBC"
        },
        {
          "external_urls": {
            "spotify": "https://open.spotify.com/artist/7D53TPVCnMEjMMKP9EKv8q"
          },
          "href": "https://api.spotify.com/v1/artists/7D53TPVCnMEjMMKP9EKv8q",
          "id": "7D53TPVCnMEjMMKP9EKv8q",
          "name": "3DDY",
          "type": "artist",
          "uri": "spotify:artist:7D53TPVCnMEjMMKP9EKv8q"
        }
      ],
      "href": "https://api.spotify.com/v1/albums/73diRAl84rievVIadGPsoc",
      "images": [
        {
          "height": 640,
          "url": "https://i.scdn.co/image/ab67616d0000b273aff3951f209e39e77a543004",
          "width": 640
        },
        {
          "height": 300,
          "url": "https://i.scdn.co/image/ab67616d00001e02aff3951f209e39e77a543004",
          "width": 300
        },
        {
          "height": 64,
          "url": "https://i.scdn.co/image/ab67616d00004851aff3951f209e39e77a543004",
          "width": 64
        }
      ],
      "name": "Hold On, Let Go",
      "release_date": "2025-08-22",
      "release_date_precision": "day",
      "total_tracks": 1,
      "type": "album",
      "uri": "spotify:album:73diRAl84rievVIadGPsoc"
    },
    "artists": [
      {
        "external_urls": {
          "spotify": "https://open.spotify.com/artist/4p5WgeiPSPpqPDs7T6OkWf"
        },
        "href": "https://api.spotify.com/v1/artists/4p5WgeiPSPpqPDs7T6OkWf",
        "id": "4p5WgeiPSPpqPDs7T6OkWf",
        "name": "ANOTR",
        "type": "artist",
        "uri": "spotify:artist:4p5WgeiPSPpqPDs7T6OkWf"
      },
      {
        "external_urls": {
          "spotify": "https://open.spotify.com/artist/4f44GWlEQdXaWl8gQ9sPBC"
        },
        "href": "https://api.spotify.com/v1/artists/4f44GWlEQdXaWl8gQ9sPBC",
        "id": "4f44GWlEQdXaWl8gQ9sPBC",
        "name": "WAYNE SNOW",
        "type": "artist",
        "uri": "spotify:artist:4f44GWlEQdXaWl8gQ9sPBC"
      },
      {
        "external_urls": {
          "spotify": "https://open.spotify.com/artist/7D53TPVCnMEjMMKP9EKv8q"
        },
        "href": "https://api.spotify.com/v1/artists/7D53TPVCnMEjMMKP9EKv8q",
        "id": "7D53TPVCnMEjMMKP9EKv8q",
        "name": "3DDY",
        "type": "artist",
        "uri": "spotify:artist:7D53TPVCnMEjMMKP9EKv8q"
      }
    ],
    "explicit": false,
    "href": "https://api.spotify.com/v1/tracks/68tOdKX9bNXD2MCFVsE5OF",
    "is_local": false,
    "name": "Hold On, Let Go",
    "preview_url": null
  },
  {
    "album": {
      "artists": [
        {
          "external_urls": {
            "spotify": "https://open.spotify.com/artist/1VJ0briNOlXRtJUAzoUJdt"
          },
          "href": "https://api.spotify.com/v1/artists/1VJ0briNOlXRtJUAzoUJdt",
          "id": "1VJ0briNOlXRtJUAzoUJdt",
          "name": "FISHER",
          "type": "artist",
          "uri": "spotify:artist:1VJ0briNOlXRtJUAzoUJdt"
        },
        {
          "external_urls": {
            "spotify": "https://open.spotify.com/artist/3CGuwWgoCYSO5Z72H5G2Ec"
          },
          "href": "https://api.spotify.com/v1/artists/3CGuwWgoCYSO5Z72H5G2Ec",
          "id": "3CGuwWgoCYSO5Z72H5G2Ec",
          "name": "Kita Alexander",
          "type": "artist",
          "uri": "spotify:artist:3CGuwWgoCYSO5Z72H5G2Ec"
        }
      ],
      "href": "https://api.spotify.com/v1/albums/5WAQTwGucEJPQLgh235Pbz",
      "images": [
        {
          "height": 640,
          "url": "https://i.scdn.co/image/ab67616d0000b273a6e3a7e65879142b2a5fe3e7",
          "width": 640
        },
        {
          "height": 300,
          "url": "https://i.scdn.co/image/ab67616d00001e02a6e3a7e65879142b2a5fe3e7",
          "width": 300
        },
        {
          "height": 64,
          "url": "https://i.scdn.co/image/ab67616d00004851a6e3a7e65879142b2a5fe3e7",
          "width": 64
        }
      ],
      "name": "Atmosphere",
      "release_date": "2023-08-11",
      "release_date_precision": "day",
      "total_tracks": 1,
      "type": "album",
      "uri": "spotify:album:5WAQTwGucEJPQLgh235Pbz"
    },
    "artists": [
      {
        "external_urls": {
          "spotify": "https://open.spotify.com/artist/1VJ0briNOlXRtJUAzoUJdt"
        },
        "href": "https://api.spotify.com/v1/artists/1VJ0briNOlXRtJUAzoUJdt",
        "id": "1VJ0briNOlXRtJUAzoUJdt",
        "name": "FISHER",
        "type": "artist",
        "uri": "spotify:artist:1VJ0briNOlXRtJUAzoUJdt"
      },
      {
        "external_urls": {
          "spotify": "https://open.spotify.com/artist/3CGuwWgoCYSO5Z72H5G2Ec"
        },
        "href": "https://api.spotify.com/v1/artists/3CGuwWgoCYSO5Z72H5G2Ec",
        "id": "3CGuwWgoCYSO5Z72H5G2Ec",
        "name": "Kita Alexander",
        "type": "artist",
        "uri": "spotify:artist:3CGuwWgoCYSO5Z72H5G2Ec"
      }
    ],
    "explicit": false,
    "href": "https://api.spotify.com/v1/tracks/63HwAAXuSV2tzIUPoHOwZa",
    "is_local": false,
    "name": "Atmosphere",
    "preview_url": null
  },
  {
    "album": {
      "artists": [
        {
          "external_urls": {
            "spotify": "https://open.spotify.com/artist/4TvhRzxIL1le2PWCeUqxQw"
          },
          "href": "https://api.spotify.com/v1/artists/4TvhRzxIL1le2PWCeUqxQw",
          "id": "4TvhRzxIL1le2PWCeUqxQw",
          "name": "The Blessed Madonna",
          "type": "artist",
          "uri": "spotify:artist:4TvhRzxIL1le2PWCeUqxQw"
        }
      ],
      "href": "https://api.spotify.com/v1/albums/0WGs5bQx4HefdubdFh1kfE",
      "images": [
        {
          "height": 640,
          "url": "https://i.scdn.co/image/ab67616d0000b273cc161028cf8ca72c2b7192b0",
          "width": 640
        },
        {
          "height": 300,
          "url": "https://i.scdn.co/image/ab67616d00001e02cc161028cf8ca72c2b7192b0",
          "width": 300
        },
        {
          "height": 64,
          "url": "https://i.scdn.co/image/ab67616d00004851cc161028cf8ca72c2b7192b0",
          "width": 64
        }
      ],
      "name": "Godspeed",
      "release_date": "2024-10-18",
      "release_date_precision": "day",
      "total_tracks": 24,
      "type": "album",
      "uri": "spotify:album:0WGs5bQx4HefdubdFh1kfE"
    },
    "artists": [
      {
        "external_urls": {
          "spotify": "https://open.spotify.com/artist/4TvhRzxIL1le2PWCeUqxQw"
        },
        "href": "https://api.spotify.com/v1/artists/4TvhRzxIL1le2PWCeUqxQw",
        "id": "4TvhRzxIL1le2PWCeUqxQw",
        "name": "The Blessed Madonna",
        "type": "artist",
        "uri": "spotify:artist:4TvhRzxIL1le2PWCeUqxQw"
      },
      {
        "external_urls": {
          "spotify": "https://open.spotify.com/artist/2s6lxOYvvCvzpHtd3VyuMj"
        },
        "href": "https://api.spotify.com/v1/artists/2s6lxOYvvCvzpHtd3VyuMj",
        "id": "2s6lxOYvvCvzpHtd3VyuMj",
        "name": "Uffie",
        "type": "artist",
        "uri": "spotify:artist:2s6lxOYvvCvzpHtd3VyuMj"
      }
    ],
    "explicit": true,
    "href": "https://api.spotify.com/v1/tracks/5W9KXaUHasNgdram95MDLN",
    "is_local": false,
    "name": "Serotonin Moonbeams",
    "preview_url": null
  },
  {
    "album": {
      "artists": [
        {
          "external_urls": {
            "spotify": "https://open.spotify.com/artist/6HabM2PUM519iIxervGWSb"
          },
          "href": "https://api.spotify.com/v1/artists/6HabM2PUM519iIxervGWSb",
          "id": "6HabM2PUM519iIxervGWSb",
          "name": "Prospa",
          "type": "artist",
          "uri": "spotify:artist:6HabM2PUM519iIxervGWSb"
        },
        {
          "external_urls": {
            "spotify": "https://open.spotify.com/artist/4zf8Awb8y1X9qwL4oiVRd6"
          },
          "href": "https://api.spotify.com/v1/artists/4zf8Awb8y1X9qwL4oiVRd6",
          "id": "4zf8Awb8y1X9qwL4oiVRd6",
          "name": "Josh Baker",
          "type": "artist",
          "uri": "spotify:artist:4zf8Awb8y1X9qwL4oiVRd6"
        },
        {
          "external_urls": {
            "spotify": "https://open.spotify.com/artist/1WR2sls6n0N1usqywvysnX"
          },
          "href": "https://api.spotify.com/v1/artists/1WR2sls6n0N1usqywvysnX",
          "id": "1WR2sls6n0N1usqywvysnX",
          "name": "RAHH",
          "type": "artist",
          "uri": "spotify:artist:1WR2sls6n0N1usqywvysnX"
        }
      ],
      "href": "https://api.spotify.com/v1/albums/7hRW5l0Tm5GCEpFHRYwxfT",
      "images": [
        {
          "height": 640,
          "url": "https://i.scdn.co/image/ab67616d0000b2731e139fad7e2df4cf8103513c",
          "width": 640
        },
        {
          "height": 300,
          "url": "https://i.scdn.co/image/ab67616d00001e021e139fad7e2df4cf8103513c",
          "width": 300
        },
        {
          "height": 64,
          "url": "https://i.scdn.co/image/ab67616d000048511e139fad7e2df4cf8103513c",
          "width": 64
        }
      ],
      "name": "You Don't Own Me (feat. RAHH)",
      "release_date": "2025-06-20",
      "release_date_precision": "day",
      "total_tracks": 1,
      "type": "album",
      "uri": "spotify:album:7hRW5l0Tm5GCEpFHRYwxfT"
    },
    "artists": [
      {
        "external_urls": {
          "spotify": "https://open.spotify.com/artist/6HabM2PUM519iIxervGWSb"
        },
        "href": "https://api.spotify.com/v1/artists/6HabM2PUM519iIxervGWSb",
        "id": "6HabM2PUM519iIxervGWSb",
        "name": "Prospa",
        "type": "artist",
        "uri": "spotify:artist:6HabM2PUM519iIxervGWSb"
      },
      {
        "external_urls": {
          "spotify": "https://open.spotify.com/artist/4zf8Awb8y1X9qwL4oiVRd6"
        },
        "href": "https://api.spotify.com/v1/artists/4zf8Awb8y1X9qwL4oiVRd6",
        "id": "4zf8Awb8y1X9qwL4oiVRd6",
        "name": "Josh Baker",
        "type": "artist",
        "uri": "spotify:artist:4zf8Awb8y1X9qwL4oiVRd6"
      },
      {
        "external_urls": {
          "spotify": "https://open.spotify.com/artist/1WR2sls6n0N1usqywvysnX"
        },
        "href": "https://api.spotify.com/v1/artists/1WR2sls6n0N1usqywvysnX",
        "id": "1WR2sls6n0N1usqywvysnX",
        "name": "RAHH",
        "type": "artist",
        "uri": "spotify:artist:1WR2sls6n0N1usqywvysnX"
      }
    ],
    "explicit": false,
    "href": "https://api.spotify.com/v1/tracks/1TsDNh8OuRcGfNX4Dz8oVl",
    "is_local": false,
    "name": "You Don't Own Me (feat. RAHH)",
    "preview_url": null
  },
  {
    "album": {
      "artists": [
        {
          "external_urls": {
            "spotify": "https://open.spotify.com/artist/7kNqXtgeIwFtelmRjWv205"
          },
          "href": "https://api.spotify.com/v1/artists/7kNqXtgeIwFtelmRjWv205",
          "id": "7kNqXtgeIwFtelmRjWv205",
          "name": "John Summit",
          "type": "artist",
          "uri": "spotify:artist:7kNqXtgeIwFtelmRjWv205"
        }
      ],
      "href": "https://api.spotify.com/v1/albums/37IWL3cLKAFT5EkQiFkDAI",
      "images": [
        {
          "height": 640,
          "url": "https://i.scdn.co/image/ab67616d0000b2732d976dc99d8d7a82c4111f8c",
          "width": 640
        },
        {
          "height": 300,
          "url": "https://i.scdn.co/image/ab67616d00001e022d976dc99d8d7a82c4111f8c",
          "width": 300
        },
        {
          "height": 64,
          "url": "https://i.scdn.co/image/ab67616d000048512d976dc99d8d7a82c4111f8c",
          "width": 64
        }
      ],
      "name": "Make Me Feel",
      "release_date": "2021-03-26",
      "release_date_precision": "day",
      "total_tracks": 2,
      "type": "album",
      "uri": "spotify:album:37IWL3cLKAFT5EkQiFkDAI"
    },
    "artists": [
      {
        "external_urls": {
          "spotify": "https://open.spotify.com/artist/7kNqXtgeIwFtelmRjWv205"
        },
        "href": "https://api.spotify.com/v1/artists/7kNqXtgeIwFtelmRjWv205",
        "id": "7kNqXtgeIwFtelmRjWv205",
        "name": "John Summit",
        "type": "artist",
        "uri": "spotify:artist:7kNqXtgeIwFtelmRjWv205"
      }
    ],
    "explicit": false,
    "href": "https://api.spotify.com/v1/tracks/0RoGOiZUCQyqAZSPBSk75T",
    "is_local": false,
    "name": "Make Me Feel",
    "preview_url": null
  },
  {
    "album": {
      "artists": [
        {
          "external_urls": {
            "spotify": "https://open.spotify.com/artist/1HBjj22wzbscIZ9sEb5dyf"
          },
          "href": "https://api.spotify.com/v1/artists/1HBjj22wzbscIZ9sEb5dyf",
          "id": "1HBjj22wzbscIZ9sEb5dyf",
          "name": "Jonas Blue",
          "type": "artist",
          "uri": "spotify:artist:1HBjj22wzbscIZ9sEb5dyf"
        },
        {
          "external_urls": {
            "spotify": "https://open.spotify.com/artist/5JsnFhU4OqgEtNXs7Sq1Vm"
          },
          "href": "https://api.spotify.com/v1/artists/5JsnFhU4OqgEtNXs7Sq1Vm",
          "id": "5JsnFhU4OqgEtNXs7Sq1Vm",
          "name": "Malive",
          "type": "artist",
          "uri": "spotify:artist:5JsnFhU4OqgEtNXs7Sq1Vm"
        }
      ],
      "href": "https://api.spotify.com/v1/albums/53b1lFTsC7lV3pieOFYZ9i",
      "images": [
        {
          "height": 640,
          "url": "https://i.scdn.co/image/ab67616d0000b2736d69d34ade62de08bff530ca",
          "width": 640
        },
        {
          "height": 300,
          "url": "https://i.scdn.co/image/ab67616d00001e026d69d34ade62de08bff530ca",
          "width": 300
        },
        {
          "height": 64,
          "url": "https://i.scdn.co/image/ab67616d000048516d69d34ade62de08bff530ca",
          "width": 64
        }
      ],
      "name": "Edge of Desire",
      "release_date": "2025-07-18",
      "release_date_precision": "day",
      "total_tracks": 2,
      "type": "album",
      "uri": "spotify:album:53b1lFTsC7lV3pieOFYZ9i"
    },
    "artists": [
      {
        "external_urls": {
          "spotify": "https://open.spotify.com/artist/1HBjj22wzbscIZ9sEb5dyf"
        },
        "href": "https://api.spotify.com/v1/artists/1HBjj22wzbscIZ9sEb5dyf",
        "id": "1HBjj22wzbscIZ9sEb5dyf",
        "name": "Jonas Blue",
        "type": "artist",
        "uri": "spotify:artist:1HBjj22wzbscIZ9sEb5dyf"
      },
      {
        "external_urls": {
          "spotify": "https://open.spotify.com/artist/5JsnFhU4OqgEtNXs7Sq1Vm"
        },
        "href": "https://api.spotify.com/v1/artists/5JsnFhU4OqgEtNXs7Sq1Vm",
        "id": "5JsnFhU4OqgEtNXs7Sq1Vm",
        "name": "Malive",
        "type": "artist",
        "uri": "spotify:artist:5JsnFhU4OqgEtNXs7Sq1Vm"
      }
    ],
    "explicit": false,
    "href": "https://api.spotify.com/v1/tracks/4A56h4B9xUuMMXoKuj18HT",
    "is_local": false,
    "name": "Edge of Desire",
    "preview_url": null
  },
  {
    "album": {
      "artists": [
        {
          "external_urls": {
            "spotify": "https://open.spotify.com/artist/1VJ0briNOlXRtJUAzoUJdt"
          },
          "href": "https://api.spotify.com/v1/artists/1VJ0briNOlXRtJUAzoUJdt",
          "id": "1VJ0briNOlXRtJUAzoUJdt",
          "name": "FISHER",
          "type": "artist",
          "uri": "spotify:artist:1VJ0briNOlXRtJUAzoUJdt"
        }
      ],
      "href": "https://api.spotify.com/v1/albums/1voOnpa4pILlDPVsrIFl8b",
      "images": [
        {
          "height": 640,
          "url": "https://i.scdn.co/image/ab67616d0000b273c9103bcebb6bf4ca93c7ad3d",
          "width": 640
        },
        {
          "height": 300,
          "url": "https://i.scdn.co/image/ab67616d00001e02c9103bcebb6bf4ca93c7ad3d",
          "width": 300
        },
        {
          "height": 64,
          "url": "https://i.scdn.co/image/ab67616d00004851c9103bcebb6bf4ca93c7ad3d",
          "width": 64
        }
      ],
      "name": "You Little Beauty",
      "release_date": "2019-05-10",
      "release_date_precision": "day",
      "total_tracks": 1,
      "type": "album",
      "uri": "spotify:album:1voOnpa4pILlDPVsrIFl8b"
    },
    "artists": [
      {
        "external_urls": {
          "spotify": "https://open.spotify.com/artist/1VJ0briNOlXRtJUAzoUJdt"
        },
        "href": "https://api.spotify.com/v1/artists/1VJ0briNOlXRtJUAzoUJdt",
        "id": "1VJ0briNOlXRtJUAzoUJdt",
        "name": "FISHER",
        "type": "artist",
        "uri": "spotify:artist:1VJ0briNOlXRtJUAzoUJdt"
      }
    ],
    "explicit": false,
    "href": "https://api.spotify.com/v1/tracks/1gRQxbfL4ULWyTosgXSbWT",
    "is_local": false,
    "name": "You Little Beauty",
    "preview_url": null
  },
  {
    "album": {
      "artists": [
        {
          "external_urls": {
            "spotify": "https://open.spotify.com/artist/6nS5roXSAGhTGr34W6n7Et"
          },
          "href": "https://api.spotify.com/v1/artists/6nS5roXSAGhTGr34W6n7Et",
          "id": "6nS5roXSAGhTGr34W6n7Et",
          "name": "Disclosure",
          "type": "artist",
          "uri": "spotify:artist:6nS5roXSAGhTGr34W6n7Et"
        }
      ],
      "href": "https://api.spotify.com/v1/albums/6wp1us3xBnYz5qldxrZXRf",
      "images": [
        {
          "height": 640,
          "url": "https://i.scdn.co/image/ab67616d0000b273355bf68fa788b6d401195b43",
          "width": 640
        },
        {
          "height": 300,
          "url": "https://i.scdn.co/image/ab67616d00001e02355bf68fa788b6d401195b43",
          "width": 300
        },
        {
          "height": 64,
          "url": "https://i.scdn.co/image/ab67616d00004851355bf68fa788b6d401195b43",
          "width": 64
        }
      ],
      "name": "ENERGY (Deluxe)",
      "release_date": "2020-08-28",
      "release_date_precision": "day",
      "total_tracks": 20,
      "type": "album",
      "uri": "spotify:album:6wp1us3xBnYz5qldxrZXRf"
    },
    "artists": [
      {
        "external_urls": {
          "spotify": "https://open.spotify.com/artist/6nS5roXSAGhTGr34W6n7Et"
        },
        "href": "https://api.spotify.com/v1/artists/6nS5roXSAGhTGr34W6n7Et",
        "id": "6nS5roXSAGhTGr34W6n7Et",
        "name": "Disclosure",
        "type": "artist",
        "uri": "spotify:artist:6nS5roXSAGhTGr34W6n7Et"
      },
      {
        "external_urls": {
          "spotify": "https://open.spotify.com/artist/7hs75D38FalYWr7BDO1WPh"
        },
        "href": "https://api.spotify.com/v1/artists/7hs75D38FalYWr7BDO1WPh",
        "id": "7hs75D38FalYWr7BDO1WPh",
        "name": "Eko Roosevelt",
        "type": "artist",
        "uri": "spotify:artist:7hs75D38FalYWr7BDO1WPh"
      }
    ],
    "explicit": false,
    "href": "https://api.spotify.com/v1/tracks/0csz09qS2n8Jo7LogHKu7j",
    "is_local": false,
    "name": "Tondo",
    "preview_url": null
  },
  {
    "album": {
      "artists": [
        {
          "external_urls": {
            "spotify": "https://open.spotify.com/artist/6zsJjoCtL1WByG0VsuFWzR"
          },
          "href": "https://api.spotify.com/v1/artists/6zsJjoCtL1WByG0VsuFWzR",
          "id": "6zsJjoCtL1WByG0VsuFWzR",
          "name": "BLOND:ISH",
          "type": "artist",
          "uri": "spotify:artist:6zsJjoCtL1WByG0VsuFWzR"
        }
      ],
      "href": "https://api.spotify.com/v1/albums/5B6cE705BTRvviiO1p4m0o",
      "images": [
        {
          "height": 640,
          "url": "https://i.scdn.co/image/ab67616d0000b2739989247ebb09f81e65420687",
          "width": 640
        },
        {
          "height": 300,
          "url": "https://i.scdn.co/image/ab67616d00001e029989247ebb09f81e65420687",
          "width": 300
        },
        {
          "height": 64,
          "url": "https://i.scdn.co/image/ab67616d000048519989247ebb09f81e65420687",
          "width": 64
        }
      ],
      "name": "Never Walk Alone",
      "release_date": "2025-02-14",
      "release_date_precision": "day",
      "total_tracks": 12,
      "type": "album",
      "uri": "spotify:album:5B6cE705BTRvviiO1p4m0o"
    },
    "artists": [
      {
        "external_urls": {
          "spotify": "https://open.spotify.com/artist/6zsJjoCtL1WByG0VsuFWzR"
        },
        "href": "https://api.spotify.com/v1/artists/6zsJjoCtL1WByG0VsuFWzR",
        "id": "6zsJjoCtL1WByG0VsuFWzR",
        "name": "BLOND:ISH",
        "type": "artist",
        "uri": "spotify:artist:6zsJjoCtL1WByG0VsuFWzR"
      },
      {
        "external_urls": {
          "spotify": "https://open.spotify.com/artist/5qMHOzLlXeOEjOncWYtRfZ"
        },
        "href": "https://api.spotify.com/v1/artists/5qMHOzLlXeOEjOncWYtRfZ",
        "id": "5qMHOzLlXeOEjOncWYtRfZ",
        "name": "Stevie Appleton",
        "type": "artist",
        "uri": "spotify:artist:5qMHOzLlXeOEjOncWYtRfZ"
      }
    ],
    "explicit": false,
    "href": "https://api.spotify.com/v1/tracks/1bE98D49uKNetOyLiaB8tG",
    "is_local": false,
    "name": "Never Walk Alone",
    "preview_url": null
  },
  {
    "album": {
      "artists": [
        {
          "external_urls": {
            "spotify": "https://open.spotify.com/artist/1VJ0briNOlXRtJUAzoUJdt"
          },
          "href": "https://api.spotify.com/v1/artists/1VJ0briNOlXRtJUAzoUJdt",
          "id": "1VJ0briNOlXRtJUAzoUJdt",
          "name": "FISHER",
          "type": "artist",
          "uri": "spotify:artist:1VJ0briNOlXRtJUAzoUJdt"
        },
        {
          "external_urls": {
            "spotify": "https://open.spotify.com/artist/4pqY01dGuzojomnVCXYbXC"
          },
          "href": "https://api.spotify.com/v1/artists/4pqY01dGuzojomnVCXYbXC",
          "id": "4pqY01dGuzojomnVCXYbXC",
          "name": "MERYLL",
          "type": "artist",
          "uri": "spotify:artist:4pqY01dGuzojomnVCXYbXC"
        }
      ],
      "href": "https://api.spotify.com/v1/albums/4aPbE5DxRmMERh3eAVY3nS",
      "images": [
        {
          "height": 640,
          "url": "https://i.scdn.co/image/ab67616d0000b273951ede297e3c2b15bf6f979f",
          "width": 640
        },
        {
          "height": 300,
          "url": "https://i.scdn.co/image/ab67616d00001e02951ede297e3c2b15bf6f979f",
          "width": 300
        },
        {
          "height": 64,
          "url": "https://i.scdn.co/image/ab67616d00004851951ede297e3c2b15bf6f979f",
          "width": 64
        }
      ],
      "name": "Yeah The Girls",
      "release_date": "2022-09-02",
      "release_date_precision": "day",
      "total_tracks": 1,
      "type": "album",
      "uri": "spotify:album:4aPbE5DxRmMERh3eAVY3nS"
    },
    "artists": [
      {
        "external_urls": {
          "spotify": "https://open.spotify.com/artist/1VJ0briNOlXRtJUAzoUJdt"
        },
        "href": "https://api.spotify.com/v1/artists/1VJ0briNOlXRtJUAzoUJdt",
        "id": "1VJ0briNOlXRtJUAzoUJdt",
        "name": "FISHER",
        "type": "artist",
        "uri": "spotify:artist:1VJ0briNOlXRtJUAzoUJdt"
      },
      {
        "external_urls": {
          "spotify": "https://open.spotify.com/artist/4pqY01dGuzojomnVCXYbXC"
        },
        "href": "https://api.spotify.com/v1/artists/4pqY01dGuzojomnVCXYbXC",
        "id": "4pqY01dGuzojomnVCXYbXC",
        "name": "MERYLL",
        "type": "artist",
        "uri": "spotify:artist:4pqY01dGuzojomnVCXYbXC"
      }
    ],
    "explicit": false,
    "href": "https://api.spotify.com/v1/tracks/1w3IvRZpHTCyGkCp8icGAa",
    "is_local": false,
    "name": "Yeah The Girls",
    "preview_url": null
  },
  {
    "album": {
      "artists": [
        {
          "external_urls": {
            "spotify": "https://open.spotify.com/artist/19VDJ9IKyBSUMDJxLsasP6"
          },
          "href": "https://api.spotify.com/v1/artists/19VDJ9IKyBSUMDJxLsasP6",
          "id": "19VDJ9IKyBSUMDJxLsasP6",
          "name": "Mr. Belt & Wezol",
          "type": "artist",
          "uri": "spotify:artist:19VDJ9IKyBSUMDJxLsasP6"
        }
      ],
      "href": "https://api.spotify.com/v1/albums/116jZe8fEmfjKBh4d8ZcDO",
      "images": [
        {
          "height": 640,
          "url": "https://i.scdn.co/image/ab67616d0000b2737ff2229742b38393c18ffa4e",
          "width": 640
        },
        {
          "height": 300,
          "url": "https://i.scdn.co/image/ab67616d00001e027ff2229742b38393c18ffa4e",
          "width": 300
        },
        {
          "height": 64,
          "url": "https://i.scdn.co/image/ab67616d000048517ff2229742b38393c18ffa4e",
          "width": 64
        }
      ],
      "name": "It's Not Right But It's Okay",
      "release_date": "2024-02-23",
      "release_date_precision": "day",
      "total_tracks": 1,
      "type": "album",
      "uri": "spotify:album:116jZe8fEmfjKBh4d8ZcDO"
    },
    "artists": [
      {
        "external_urls": {
          "spotify": "https://open.spotify.com/artist/19VDJ9IKyBSUMDJxLsasP6"
        },
        "href": "https://api.spotify.com/v1/artists/19VDJ9IKyBSUMDJxLsasP6",
        "id": "19VDJ9IKyBSUMDJxLsasP6",
        "name": "Mr. Belt & Wezol",
        "type": "artist",
        "uri": "spotify:artist:19VDJ9IKyBSUMDJxLsasP6"
      }
    ],
    "explicit": false,
    "href": "https://api.spotify.com/v1/tracks/5OFVzqSeFxGpvDGyHvVeLj",
    "is_local": false,
    "name": "It's Not Right But It's Okay",
    "preview_url": null
  },
  {
    "album": {
      "artists": [
        {
          "external_urls": {
            "spotify": "https://open.spotify.com/artist/2AsusXITU8P25dlRNhcAbG"
          },
          "href": "https://api.spotify.com/v1/artists/2AsusXITU8P25dlRNhcAbG",
          "id": "2AsusXITU8P25dlRNhcAbG",
          "name": "Gotye",
          "type": "artist",
          "uri": "spotify:artist:2AsusXITU8P25dlRNhcAbG"
        },
        {
          "external_urls": {
            "spotify": "https://open.spotify.com/artist/1VJ0briNOlXRtJUAzoUJdt"
          },
          "href": "https://api.spotify.com/v1/artists/1VJ0briNOlXRtJUAzoUJdt",
          "id": "1VJ0briNOlXRtJUAzoUJdt",
          "name": "FISHER",
          "type": "artist",
          "uri": "spotify:artist:1VJ0briNOlXRtJUAzoUJdt"
        },
        {
          "external_urls": {
            "spotify": "https://open.spotify.com/artist/5Igpc9iLZ3YGtKeYfSrrOE"
          },
          "href": "https://api.spotify.com/v1/artists/5Igpc9iLZ3YGtKeYfSrrOE",
          "id": "5Igpc9iLZ3YGtKeYfSrrOE",
          "name": "Chris Lake",
          "type": "artist",
          "uri": "spotify:artist:5Igpc9iLZ3YGtKeYfSrrOE"
        }
      ],
      "href": "https://api.spotify.com/v1/albums/5eKQYtDqVmrHPZoKHG1LlH",
      "images": [
        {
          "height": 640,
          "url": "https://i.scdn.co/image/ab67616d0000b273decbf9beecb3cb749ce3a2e2",
          "width": 640
        },
        {
          "height": 300,
          "url": "https://i.scdn.co/image/ab67616d00001e02decbf9beecb3cb749ce3a2e2",
          "width": 300
        },
        {
          "height": 64,
          "url": "https://i.scdn.co/image/ab67616d00004851decbf9beecb3cb749ce3a2e2",
          "width": 64
        }
      ],
      "name": "Somebody (2024)",
      "release_date": "2024-02-09",
      "release_date_precision": "day",
      "total_tracks": 1,
      "type": "album",
      "uri": "spotify:album:5eKQYtDqVmrHPZoKHG1LlH"
    },
    "artists": [
      {
        "external_urls": {
          "spotify": "https://open.spotify.com/artist/2AsusXITU8P25dlRNhcAbG"
        },
        "href": "https://api.spotify.com/v1/artists/2AsusXITU8P25dlRNhcAbG",
        "id": "2AsusXITU8P25dlRNhcAbG",
        "name": "Gotye",
        "type": "artist",
        "uri": "spotify:artist:2AsusXITU8P25dlRNhcAbG"
      },
      {
        "external_urls": {
          "spotify": "https://open.spotify.com/artist/1VJ0briNOlXRtJUAzoUJdt"
        },
        "href": "https://api.spotify.com/v1/artists/1VJ0briNOlXRtJUAzoUJdt",
        "id": "1VJ0briNOlXRtJUAzoUJdt",
        "name": "FISHER",
        "type": "artist",
        "uri": "spotify:artist:1VJ0briNOlXRtJUAzoUJdt"
      },
      {
        "external_urls": {
          "spotify": "https://open.spotify.com/artist/5Igpc9iLZ3YGtKeYfSrrOE"
        },
        "href": "https://api.spotify.com/v1/artists/5Igpc9iLZ3YGtKeYfSrrOE",
        "id": "5Igpc9iLZ3YGtKeYfSrrOE",
        "name": "Chris Lake",
        "type": "artist",
        "uri": "spotify:artist:5Igpc9iLZ3YGtKeYfSrrOE"
      },
      {
        "external_urls": {
          "spotify": "https://open.spotify.com/artist/6hk7Yq1DU9QcCCrz9uc0Ti"
        },
        "href": "https://api.spotify.com/v1/artists/6hk7Yq1DU9QcCCrz9uc0Ti",
        "id": "6hk7Yq1DU9QcCCrz9uc0Ti",
        "name": "Kimbra",
        "type": "artist",
        "uri": "spotify:artist:6hk7Yq1DU9QcCCrz9uc0Ti"
      },
      {
        "external_urls": {
          "spotify": "https://open.spotify.com/artist/5fAwPpS78sokZdpktoSUE8"
        },
        "href": "https://api.spotify.com/v1/artists/5fAwPpS78sokZdpktoSUE8",
        "id": "5fAwPpS78sokZdpktoSUE8",
        "name": "Sante Sansone",
        "type": "artist",
        "uri": "spotify:artist:5fAwPpS78sokZdpktoSUE8"
      }
    ],
    "explicit": false,
    "href": "https://api.spotify.com/v1/tracks/0agQ9vIV7NP4dntGKLcCXO",
    "is_local": false,
    "name": "Somebody (2024)",
    "preview_url": null
  },
  {
    "album": {
      "artists": [
        {
          "external_urls": {
            "spotify": "https://open.spotify.com/artist/1vCWHaC5f2uS3yhpwWbIA6"
          },
          "href": "https://api.spotify.com/v1/artists/1vCWHaC5f2uS3yhpwWbIA6",
          "id": "1vCWHaC5f2uS3yhpwWbIA6",
          "name": "Avicii",
          "type": "artist",
          "uri": "spotify:artist:1vCWHaC5f2uS3yhpwWbIA6"
        }
      ],
      "href": "https://api.spotify.com/v1/albums/5VPw18vPykfaX5s3jiS0Ox",
      "images": [
        {
          "height": 640,
          "url": "https://i.scdn.co/image/ab67616d0000b273d586098ba36b54d4167de337",
          "width": 640
        },
        {
          "height": 300,
          "url": "https://i.scdn.co/image/ab67616d00001e02d586098ba36b54d4167de337",
          "width": 300
        },
        {
          "height": 64,
          "url": "https://i.scdn.co/image/ab67616d00004851d586098ba36b54d4167de337",
          "width": 64
        }
      ],
      "name": "Avicii Forever",
      "release_date": "2025-05-16",
      "release_date_precision": "day",
      "total_tracks": 20,
      "type": "album",
      "uri": "spotify:album:5VPw18vPykfaX5s3jiS0Ox"
    },
    "artists": [
      {
        "external_urls": {
          "spotify": "https://open.spotify.com/artist/1vCWHaC5f2uS3yhpwWbIA6"
        },
        "href": "https://api.spotify.com/v1/artists/1vCWHaC5f2uS3yhpwWbIA6",
        "id": "1vCWHaC5f2uS3yhpwWbIA6",
        "name": "Avicii",
        "type": "artist",
        "uri": "spotify:artist:1vCWHaC5f2uS3yhpwWbIA6"
      },
      {
        "external_urls": {
          "spotify": "https://open.spotify.com/artist/5ChF3i92IPZHduM7jN3dpg"
        },
        "href": "https://api.spotify.com/v1/artists/5ChF3i92IPZHduM7jN3dpg",
        "id": "5ChF3i92IPZHduM7jN3dpg",
        "name": "Nicky Romero",
        "type": "artist",
        "uri": "spotify:artist:5ChF3i92IPZHduM7jN3dpg"
      }
    ],
    "explicit": false,
    "href": "https://api.spotify.com/v1/tracks/1lpGsHdCpWiTvrFitLakBo",
    "is_local": false,
    "name": "I Could Be The One (Avicii Vs. Nicky Romero) - Radio Edit",
    "preview_url": null
  },
  {
    "album": {
      "artists": [
        {
          "external_urls": {
            "spotify": "https://open.spotify.com/artist/7kNqXtgeIwFtelmRjWv205"
          },
          "href": "https://api.spotify.com/v1/artists/7kNqXtgeIwFtelmRjWv205",
          "id": "7kNqXtgeIwFtelmRjWv205",
          "name": "John Summit",
          "type": "artist",
          "uri": "spotify:artist:7kNqXtgeIwFtelmRjWv205"
        }
      ],
      "href": "https://api.spotify.com/v1/albums/2pHm3ZP2R3phzCYi7ilGN2",
      "images": [
        {
          "height": 640,
          "url": "https://i.scdn.co/image/ab67616d0000b273ac2be70b09319ac92b074fde",
          "width": 640
        },
        {
          "height": 300,
          "url": "https://i.scdn.co/image/ab67616d00001e02ac2be70b09319ac92b074fde",
          "width": 300
        },
        {
          "height": 64,
          "url": "https://i.scdn.co/image/ab67616d00004851ac2be70b09319ac92b074fde",
          "width": 64
        }
      ],
      "name": "Comfort In Chaos",
      "release_date": "2024-07-12",
      "release_date_precision": "day",
      "total_tracks": 12,
      "type": "album",
      "uri": "spotify:album:2pHm3ZP2R3phzCYi7ilGN2"
    },
    "artists": [
      {
        "external_urls": {
          "spotify": "https://open.spotify.com/artist/7kNqXtgeIwFtelmRjWv205"
        },
        "href": "https://api.spotify.com/v1/artists/7kNqXtgeIwFtelmRjWv205",
        "id": "7kNqXtgeIwFtelmRjWv205",
        "name": "John Summit",
        "type": "artist",
        "uri": "spotify:artist:7kNqXtgeIwFtelmRjWv205"
      },
      {
        "external_urls": {
          "spotify": "https://open.spotify.com/artist/0QaSiI5TLA4N7mcsdxShDO"
        },
        "href": "https://api.spotify.com/v1/artists/0QaSiI5TLA4N7mcsdxShDO",
        "id": "0QaSiI5TLA4N7mcsdxShDO",
        "name": "Sub Focus",
        "type": "artist",
        "uri": "spotify:artist:0QaSiI5TLA4N7mcsdxShDO"
      },
      {
        "external_urls": {
          "spotify": "https://open.spotify.com/artist/4dHGNdVhBxCJUyMk9dR727"
        },
        "href": "https://api.spotify.com/v1/artists/4dHGNdVhBxCJUyMk9dR727",
        "id": "4dHGNdVhBxCJUyMk9dR727",
        "name": "Julia Church",
        "type": "artist",
        "uri": "spotify:artist:4dHGNdVhBxCJUyMk9dR727"
      }
    ],
    "explicit": false,
    "href": "https://api.spotify.com/v1/tracks/4CfcXnwLf2MUfnjCnqUMvj",
    "is_local": false,
    "name": "Go Back (feat. Julia Church)",
    "preview_url": null
  },
  {
    "album": {
      "artists": [
        {
          "external_urls": {
            "spotify": "https://open.spotify.com/artist/3BxjasMelf9pKaE4f7Y0So"
          },
          "href": "https://api.spotify.com/v1/artists/3BxjasMelf9pKaE4f7Y0So",
          "id": "3BxjasMelf9pKaE4f7Y0So",
          "name": "Chris Stussy",
          "type": "artist",
          "uri": "spotify:artist:3BxjasMelf9pKaE4f7Y0So"
        }
      ],
      "href": "https://api.spotify.com/v1/albums/0MsZjOcL3T5uqkB58vDD7E",
      "images": [
        {
          "height": 640,
          "url": "https://i.scdn.co/image/ab67616d0000b273e048f5330727a0938af67127",
          "width": 640
        },
        {
          "height": 300,
          "url": "https://i.scdn.co/image/ab67616d00001e02e048f5330727a0938af67127",
          "width": 300
        },
        {
          "height": 64,
          "url": "https://i.scdn.co/image/ab67616d00004851e048f5330727a0938af67127",
          "width": 64
        }
      ],
      "name": "Desire",
      "release_date": "2024-02-09",
      "release_date_precision": "day",
      "total_tracks": 1,
      "type": "album",
      "uri": "spotify:album:0MsZjOcL3T5uqkB58vDD7E"
    },
    "artists": [
      {
        "external_urls": {
          "spotify": "https://open.spotify.com/artist/3BxjasMelf9pKaE4f7Y0So"
        },
        "href": "https://api.spotify.com/v1/artists/3BxjasMelf9pKaE4f7Y0So",
        "id": "3BxjasMelf9pKaE4f7Y0So",
        "name": "Chris Stussy",
        "type": "artist",
        "uri": "spotify:artist:3BxjasMelf9pKaE4f7Y0So"
      }
    ],
    "explicit": false,
    "href": "https://api.spotify.com/v1/tracks/3uahZPFLqwDp0Jje5K60q4",
    "is_local": false,
    "name": "Desire",
    "preview_url": null
  },
  {
    "album": {
      "artists": [
        {
          "external_urls": {
            "spotify": "https://open.spotify.com/artist/2YEnrpAWWaNRFumgde1lLH"
          },
          "href": "https://api.spotify.com/v1/artists/2YEnrpAWWaNRFumgde1lLH",
          "id": "2YEnrpAWWaNRFumgde1lLH",
          "name": "Oden & Fatzo",
          "type": "artist",
          "uri": "spotify:artist:2YEnrpAWWaNRFumgde1lLH"
        }
      ],
      "href": "https://api.spotify.com/v1/albums/3L1NLn5rcrmV4uVqgaoTI7",
      "images": [
        {
          "height": 640,
          "url": "https://i.scdn.co/image/ab67616d0000b2732ade3f3d0fb1a94a5b289efd",
          "width": 640
        },
        {
          "height": 300,
          "url": "https://i.scdn.co/image/ab67616d00001e022ade3f3d0fb1a94a5b289efd",
          "width": 300
        },
        {
          "height": 64,
          "url": "https://i.scdn.co/image/ab67616d000048512ade3f3d0fb1a94a5b289efd",
          "width": 64
        }
      ],
      "name": "Lauren (I Can't Stay Forever)",
      "release_date": "2021-10-08",
      "release_date_precision": "day",
      "total_tracks": 1,
      "type": "album",
      "uri": "spotify:album:3L1NLn5rcrmV4uVqgaoTI7"
    },
    "artists": [
      {
        "external_urls": {
          "spotify": "https://open.spotify.com/artist/2YEnrpAWWaNRFumgde1lLH"
        },
        "href": "https://api.spotify.com/v1/artists/2YEnrpAWWaNRFumgde1lLH",
        "id": "2YEnrpAWWaNRFumgde1lLH",
        "name": "Oden & Fatzo",
        "type": "artist",
        "uri": "spotify:artist:2YEnrpAWWaNRFumgde1lLH"
      }
    ],
    "explicit": false,
    "href": "https://api.spotify.com/v1/tracks/33tYADyL2aZctrvR59K1bQ",
    "is_local": false,
    "name": "Lauren (I Can't Stay Forever)",
    "preview_url": null
  },
  {
    "album": {
      "artists": [
        {
          "external_urls": {
            "spotify": "https://open.spotify.com/artist/2QsynagSdAqZj3U9HgDzjD"
          },
          "href": "https://api.spotify.com/v1/artists/2QsynagSdAqZj3U9HgDzjD",
          "id": "2QsynagSdAqZj3U9HgDzjD",
          "name": "Bob Marley & The Wailers",
          "type": "artist",
          "uri": "spotify:artist:2QsynagSdAqZj3U9HgDzjD"
        },
        {
          "external_urls": {
            "spotify": "https://open.spotify.com/artist/1VJ0briNOlXRtJUAzoUJdt"
          },
          "href": "https://api.spotify.com/v1/artists/1VJ0briNOlXRtJUAzoUJdt",
          "id": "1VJ0briNOlXRtJUAzoUJdt",
          "name": "FISHER",
          "type": "artist",
          "uri": "spotify:artist:1VJ0briNOlXRtJUAzoUJdt"
        }
      ],
      "href": "https://api.spotify.com/v1/albums/7JIcY8DOxlyJKAW3Dl3sWk",
      "images": [
        {
          "height": 640,
          "url": "https://i.scdn.co/image/ab67616d0000b2737e536112cde0150fdaec65b6",
          "width": 640
        },
        {
          "height": 300,
          "url": "https://i.scdn.co/image/ab67616d00001e027e536112cde0150fdaec65b6",
          "width": 300
        },
        {
          "height": 64,
          "url": "https://i.scdn.co/image/ab67616d000048517e536112cde0150fdaec65b6",
          "width": 64
        }
      ],
      "name": "Jamming (FISHER Rework)",
      "release_date": "2024-02-08",
      "release_date_precision": "day",
      "total_tracks": 1,
      "type": "album",
      "uri": "spotify:album:7JIcY8DOxlyJKAW3Dl3sWk"
    },
    "artists": [
      {
        "external_urls": {
          "spotify": "https://open.spotify.com/artist/2QsynagSdAqZj3U9HgDzjD"
        },
        "href": "https://api.spotify.com/v1/artists/2QsynagSdAqZj3U9HgDzjD",
        "id": "2QsynagSdAqZj3U9HgDzjD",
        "name": "Bob Marley & The Wailers",
        "type": "artist",
        "uri": "spotify:artist:2QsynagSdAqZj3U9HgDzjD"
      },
      {
        "external_urls": {
          "spotify": "https://open.spotify.com/artist/1VJ0briNOlXRtJUAzoUJdt"
        },
        "href": "https://api.spotify.com/v1/artists/1VJ0briNOlXRtJUAzoUJdt",
        "id": "1VJ0briNOlXRtJUAzoUJdt",
        "name": "FISHER",
        "type": "artist",
        "uri": "spotify:artist:1VJ0briNOlXRtJUAzoUJdt"
      }
    ],
    "explicit": false,
    "href": "https://api.spotify.com/v1/tracks/2gKewcQZEV1fqoWH81RUDk",
    "is_local": false,
    "name": "Jamming - FISHER Rework",
    "preview_url": null
  }
]